{
  "date": "2026-04-21",
  "unit": "張",
  "stocks": [
    {
      "rank": 1,
      "name": "合晶",
      "code": "6182",
      "brokers": [
        {
          "rank": 1,
          "name": "元大",
          "buy": 19384,
          "sell": 18084,
          "net": 1300
        },
        {
          "rank": 2,
          "name": "凱基",
          "buy": 11156,
          "sell": 7139,
          "net": 4017
        },
        {
          "rank": 3,
          "name": "富邦",
          "buy": 6301,
          "sell": 6312,
          "net": -11
        },
        {
          "rank": 4,
          "name": "群益",
          "buy": 2748,
          "sell": 5025,
          "net": -2277
        },
        {
          "rank": 5,
          "name": "國泰綜合",
          "buy": 3551,
          "sell": 3214,
          "net": 337
        },
        {
          "rank": 6,
          "name": "永豐金",
          "buy": 2768,
          "sell": 3779,
          "net": -1011
        },
        {
          "rank": 7,
          "name": "台新",
          "buy": 2750,
          "sell": 3791,
          "net": -1041
        },
        {
          "rank": 8,
          "name": "兆豐",
          "buy": 3538,
          "sell": 2176,
          "net": 1362
        },
        {
          "rank": 9,
          "name": "統一",
          "buy": 2573,
          "sell": 2599,
          "net": -26
        },
        {
          "rank": 10,
          "name": "華南永昌",
          "buy": 1594,
          "sell": 2220,
          "net": -626
        },
        {
          "rank": 11,
          "name": "國票",
          "buy": 2639,
          "sell": 864,
          "net": 1775
        },
        {
          "rank": 12,
          "name": "摩根士丹利",
          "buy": 2509,
          "sell": 706,
          "net": 1803
        },
        {
          "rank": 13,
          "name": "美商高盛亞",
          "buy": 1849,
          "sell": 1129,
          "net": 720
        },
        {
          "rank": 14,
          "name": "玉山證券",
          "buy": 1240,
          "sell": 1601,
          "net": -361
        },
        {
          "rank": 15,
          "name": "星洲瑞銀",
          "buy": 1394,
          "sell": 1432,
          "net": -38
        }
      ],
      "total_net": 5923
    },
    {
      "rank": 2,
      "name": "富喬",
      "code": "1815",
      "brokers": [
        {
          "rank": 1,
          "name": "元大",
          "buy": 13602,
          "sell": 11007,
          "net": 2595
        },
        {
          "rank": 2,
          "name": "凱基",
          "buy": 5921,
          "sell": 5637,
          "net": 284
        },
        {
          "rank": 3,
          "name": "富邦",
          "buy": 4285,
          "sell": 5035,
          "net": -750
        },
        {
          "rank": 4,
          "name": "永豐金",
          "buy": 3182,
          "sell": 3531,
          "net": -349
        },
        {
          "rank": 5,
          "name": "兆豐",
          "buy": 2100,
          "sell": 4190,
          "net": -2090
        },
        {
          "rank": 6,
          "name": "國泰綜合",
          "buy": 3175,
          "sell": 2861,
          "net": 314
        },
        {
          "rank": 7,
          "name": "華南永昌",
          "buy": 4182,
          "sell": 1588,
          "net": 2594
        },
        {
          "rank": 8,
          "name": "台新",
          "buy": 2894,
          "sell": 2370,
          "net": 524
        },
        {
          "rank": 9,
          "name": "統一",
          "buy": 1741,
          "sell": 3220,
          "net": -1479
        },
        {
          "rank": 10,
          "name": "群益",
          "buy": 2333,
          "sell": 1630,
          "net": 703
        },
        {
          "rank": 11,
          "name": "摩根大通",
          "buy": 1536,
          "sell": 1952,
          "net": -416
        },
        {
          "rank": 12,
          "name": "玉山證券",
          "buy": 1260,
          "sell": 1846,
          "net": -586
        },
        {
          "rank": 13,
          "name": "星洲瑞銀",
          "buy": 1319,
          "sell": 1678,
          "net": -359
        },
        {
          "rank": 14,
          "name": "新光",
          "buy": 1282,
          "sell": 1625,
          "net": -343
        },
        {
          "rank": 15,
          "name": "美商高盛亞",
          "buy": 555,
          "sell": 1360,
          "net": -805
        }
      ],
      "total_net": -163
    },
    {
      "rank": 3,
      "name": "金居",
      "code": "8358",
      "brokers": [
        {
          "rank": 1,
          "name": "元大",
          "buy": 15748,
          "sell": 13493,
          "net": 2255
        },
        {
          "rank": 2,
          "name": "凱基",
          "buy": 7196,
          "sell": 7660,
          "net": -464
        },
        {
          "rank": 3,
          "name": "國泰綜合",
          "buy": 4706,
          "sell": 3643,
          "net": 1063
        },
        {
          "rank": 4,
          "name": "富邦",
          "buy": 3490,
          "sell": 4852,
          "net": -1362
        },
        {
          "rank": 5,
          "name": "永豐金",
          "buy": 2930,
          "sell": 3025,
          "net": -95
        },
        {
          "rank": 6,
          "name": "群益",
          "buy": 3181,
          "sell": 2432,
          "net": 749
        },
        {
          "rank": 7,
          "name": "台新",
          "buy": 2724,
          "sell": 2197,
          "net": 527
        },
        {
          "rank": 8,
          "name": "統一",
          "buy": 2346,
          "sell": 2248,
          "net": 98
        },
        {
          "rank": 9,
          "name": "華南永昌",
          "buy": 1664,
          "sell": 1434,
          "net": 230
        },
        {
          "rank": 10,
          "name": "星洲瑞銀",
          "buy": 1513,
          "sell": 1537,
          "net": -24
        },
        {
          "rank": 11,
          "name": "摩根士丹利",
          "buy": 274,
          "sell": 2471,
          "net": -2197
        },
        {
          "rank": 12,
          "name": "兆豐",
          "buy": 1379,
          "sell": 1262,
          "net": 117
        },
        {
          "rank": 13,
          "name": "國票",
          "buy": 635,
          "sell": 1669,
          "net": -1034
        },
        {
          "rank": 14,
          "name": "新光",
          "buy": 1318,
          "sell": 977,
          "net": 341
        },
        {
          "rank": 15,
          "name": "玉山證券",
          "buy": 1364,
          "sell": 901,
          "net": 463
        }
      ],
      "total_net": 667
    },
    {
      "rank": 4,
      "name": "穩懋",
      "code": "3105",
      "brokers": [
        {
          "rank": 1,
          "name": "元大",
          "buy": 13536,
          "sell": 11063,
          "net": 2473
        },
        {
          "rank": 2,
          "name": "凱基",
          "buy": 5985,
          "sell": 7514,
          "net": -1529
        },
        {
          "rank": 3,
          "name": "國泰綜合",
          "buy": 3868,
          "sell": 3410,
          "net": 458
        },
        {
          "rank": 4,
          "name": "台新",
          "buy": 3219,
          "sell": 2578,
          "net": 641
        },
        {
          "rank": 5,
          "name": "富邦",
          "buy": 2922,
          "sell": 2852,
          "net": 70
        },
        {
          "rank": 6,
          "name": "永豐金",
          "buy": 2659,
          "sell": 2261,
          "net": 398
        },
        {
          "rank": 7,
          "name": "群益",
          "buy": 2243,
          "sell": 2123,
          "net": 120
        },
        {
          "rank": 8,
          "name": "摩根士丹利",
          "buy": 1962,
          "sell": 1994,
          "net": -32
        },
        {
          "rank": 9,
          "name": "摩根大通",
          "buy": 1921,
          "sell": 1997,
          "net": -76
        },
        {
          "rank": 10,
          "name": "星洲瑞銀",
          "buy": 1046,
          "sell": 2099,
          "net": -1053
        },
        {
          "rank": 11,
          "name": "美商高盛亞",
          "buy": 847,
          "sell": 2291,
          "net": -1444
        },
        {
          "rank": 12,
          "name": "統一",
          "buy": 1176,
          "sell": 1831,
          "net": -655
        },
        {
          "rank": 13,
          "name": "美林證券",
          "buy": 1743,
          "sell": 768,
          "net": 975
        },
        {
          "rank": 14,
          "name": "玉山證券",
          "buy": 1641,
          "sell": 757,
          "net": 884
        },
        {
          "rank": 15,
          "name": "華南永昌",
          "buy": 1168,
          "sell": 1101,
          "net": 67
        }
      ],
      "total_net": 1297
    },
    {
      "rank": 5,
      "name": "凱崴",
      "code": "5498",
      "brokers": [
        {
          "rank": 1,
          "name": "富邦",
          "buy": 8985,
          "sell": 11925,
          "net": -2940
        },
        {
          "rank": 2,
          "name": "元大",
          "buy": 9036,
          "sell": 9459,
          "net": -423
        },
        {
          "rank": 3,
          "name": "凱基",
          "buy": 6648,
          "sell": 6186,
          "net": 462
        },
        {
          "rank": 4,
          "name": "永豐金",
          "buy": 2180,
          "sell": 3239,
          "net": -1059
        },
        {
          "rank": 5,
          "name": "台新",
          "buy": 2077,
          "sell": 2515,
          "net": -438
        },
        {
          "rank": 6,
          "name": "國泰綜合",
          "buy": 2030,
          "sell": 2286,
          "net": -256
        },
        {
          "rank": 7,
          "name": "華南永昌",
          "buy": 1534,
          "sell": 1960,
          "net": -426
        },
        {
          "rank": 8,
          "name": "群益",
          "buy": 1681,
          "sell": 1551,
          "net": 130
        },
        {
          "rank": 9,
          "name": "統一",
          "buy": 2028,
          "sell": 1065,
          "net": 963
        },
        {
          "rank": 10,
          "name": "星洲瑞銀",
          "buy": 2133,
          "sell": 177,
          "net": 1956
        },
        {
          "rank": 11,
          "name": "兆豐",
          "buy": 1016,
          "sell": 1222,
          "net": -206
        },
        {
          "rank": 12,
          "name": "玉山證券",
          "buy": 1161,
          "sell": 960,
          "net": 201
        },
        {
          "rank": 13,
          "name": "新光",
          "buy": 906,
          "sell": 899,
          "net": 7
        },
        {
          "rank": 14,
          "name": "美商高盛亞",
          "buy": 1189,
          "sell": 525,
          "net": 664
        },
        {
          "rank": 15,
          "name": "國票",
          "buy": 1006,
          "sell": 671,
          "net": 335
        }
      ],
      "total_net": -1030
    },
    {
      "rank": 6,
      "name": "世界",
      "code": "5347",
      "brokers": [
        {
          "rank": 1,
          "name": "元大",
          "buy": 11122,
          "sell": 7584,
          "net": 3538
        },
        {
          "rank": 2,
          "name": "凱基",
          "buy": 4845,
          "sell": 5066,
          "net": -221
        },
        {
          "rank": 3,
          "name": "富邦",
          "buy": 3457,
          "sell": 3324,
          "net": 133
        },
        {
          "rank": 4,
          "name": "摩根士丹利",
          "buy": 2912,
          "sell": 3569,
          "net": -657
        },
        {
          "rank": 5,
          "name": "台新",
          "buy": 3489,
          "sell": 2354,
          "net": 1135
        },
        {
          "rank": 6,
          "name": "群益",
          "buy": 2786,
          "sell": 2693,
          "net": 93
        },
        {
          "rank": 7,
          "name": "星洲瑞銀",
          "buy": 1100,
          "sell": 3756,
          "net": -2656
        },
        {
          "rank": 8,
          "name": "永豐金",
          "buy": 2096,
          "sell": 1449,
          "net": 647
        },
        {
          "rank": 9,
          "name": "國泰綜合",
          "buy": 1795,
          "sell": 1247,
          "net": 548
        },
        {
          "rank": 10,
          "name": "港商野村",
          "buy": 171,
          "sell": 2737,
          "net": -2566
        },
        {
          "rank": 11,
          "name": "美商高盛亞",
          "buy": 688,
          "sell": 1788,
          "net": -1100
        },
        {
          "rank": 12,
          "name": "美林證券",
          "buy": 81,
          "sell": 2259,
          "net": -2178
        },
        {
          "rank": 13,
          "name": "摩根大通",
          "buy": 738,
          "sell": 1510,
          "net": -772
        },
        {
          "rank": 14,
          "name": "華南永昌",
          "buy": 1424,
          "sell": 693,
          "net": 731
        },
        {
          "rank": 15,
          "name": "統一",
          "buy": 1441,
          "sell": 601,
          "net": 840
        }
      ],
      "total_net": -2485
    },
    {
      "rank": 7,
      "name": "亞電",
      "code": "4939",
      "brokers": [
        {
          "rank": 1,
          "name": "元大",
          "buy": 6806,
          "sell": 7212,
          "net": -406
        },
        {
          "rank": 2,
          "name": "凱基",
          "buy": 4404,
          "sell": 6414,
          "net": -2010
        },
        {
          "rank": 3,
          "name": "富邦",
          "buy": 2629,
          "sell": 2386,
          "net": 243
        },
        {
          "rank": 4,
          "name": "國泰綜合",
          "buy": 3120,
          "sell": 1883,
          "net": 1237
        },
        {
          "rank": 5,
          "name": "台新",
          "buy": 2194,
          "sell": 1997,
          "net": 197
        },
        {
          "rank": 6,
          "name": "永豐金",
          "buy": 1995,
          "sell": 1569,
          "net": 426
        },
        {
          "rank": 7,
          "name": "群益",
          "buy": 1400,
          "sell": 1347,
          "net": 53
        },
        {
          "rank": 8,
          "name": "華南永昌",
          "buy": 1226,
          "sell": 919,
          "net": 307
        },
        {
          "rank": 9,
          "name": "兆豐",
          "buy": 1020,
          "sell": 920,
          "net": 100
        },
        {
          "rank": 10,
          "name": "玉山證券",
          "buy": 942,
          "sell": 654,
          "net": 288
        },
        {
          "rank": 11,
          "name": "星洲瑞銀",
          "buy": 770,
          "sell": 697,
          "net": 73
        },
        {
          "rank": 12,
          "name": "新光",
          "buy": 746,
          "sell": 695,
          "net": 51
        },
        {
          "rank": 13,
          "name": "統一",
          "buy": 646,
          "sell": 764,
          "net": -118
        },
        {
          "rank": 14,
          "name": "中國信託證",
          "buy": 662,
          "sell": 575,
          "net": 87
        },
        {
          "rank": 15,
          "name": "美商高盛亞",
          "buy": 471,
          "sell": 758,
          "net": -287
        }
      ],
      "total_net": 241
    },
    {
      "rank": 8,
      "name": "威剛",
      "code": "3260",
      "brokers": [
        {
          "rank": 1,
          "name": "元大",
          "buy": 4231,
          "sell": 6632,
          "net": -2401
        },
        {
          "rank": 2,
          "name": "凱基",
          "buy": 5407,
          "sell": 3663,
          "net": 1744
        },
        {
          "rank": 3,
          "name": "富邦",
          "buy": 3678,
          "sell": 3037,
          "net": 641
        },
        {
          "rank": 4,
          "name": "摩根士丹利",
          "buy": 3242,
          "sell": 532,
          "net": 2710
        },
        {
          "rank": 5,
          "name": "永豐金",
          "buy": 1296,
          "sell": 2352,
          "net": -1056
        },
        {
          "rank": 6,
          "name": "台新",
          "buy": 1118,
          "sell": 2278,
          "net": -1160
        },
        {
          "rank": 7,
          "name": "國泰綜合",
          "buy": 965,
          "sell": 1760,
          "net": -795
        },
        {
          "rank": 8,
          "name": "群益",
          "buy": 870,
          "sell": 1682,
          "net": -812
        },
        {
          "rank": 9,
          "name": "星洲瑞銀",
          "buy": 2081,
          "sell": 411,
          "net": 1670
        },
        {
          "rank": 10,
          "name": "港商野村",
          "buy": 2160,
          "sell": 55,
          "net": 2105
        },
        {
          "rank": 11,
          "name": "華南永昌",
          "buy": 545,
          "sell": 1341,
          "net": -796
        },
        {
          "rank": 12,
          "name": "美商高盛亞",
          "buy": 1469,
          "sell": 177,
          "net": 1292
        },
        {
          "rank": 13,
          "name": "國票",
          "buy": 686,
          "sell": 850,
          "net": -164
        },
        {
          "rank": 14,
          "name": "兆豐",
          "buy": 477,
          "sell": 960,
          "net": -483
        },
        {
          "rank": 15,
          "name": "玉山證券",
          "buy": 421,
          "sell": 870,
          "net": -449
        }
      ],
      "total_net": 2046
    },
    {
      "rank": 9,
      "name": "鉅橡",
      "code": "8074",
      "brokers": [
        {
          "rank": 1,
          "name": "元大",
          "buy": 7449,
          "sell": 6784,
          "net": 665
        },
        {
          "rank": 2,
          "name": "富邦",
          "buy": 1931,
          "sell": 3012,
          "net": -1081
        },
        {
          "rank": 3,
          "name": "國泰綜合",
          "buy": 2202,
          "sell": 1914,
          "net": 288
        },
        {
          "rank": 4,
          "name": "永豐金",
          "buy": 1946,
          "sell": 1669,
          "net": 277
        },
        {
          "rank": 5,
          "name": "凱基",
          "buy": 1603,
          "sell": 1681,
          "net": -78
        },
        {
          "rank": 6,
          "name": "美商高盛亞",
          "buy": 1154,
          "sell": 1561,
          "net": -407
        },
        {
          "rank": 7,
          "name": "群益",
          "buy": 1267,
          "sell": 1425,
          "net": -158
        },
        {
          "rank": 8,
          "name": "台新",
          "buy": 1281,
          "sell": 1249,
          "net": 32
        },
        {
          "rank": 9,
          "name": "新光",
          "buy": 966,
          "sell": 761,
          "net": 205
        },
        {
          "rank": 10,
          "name": "統一",
          "buy": 715,
          "sell": 978,
          "net": -263
        },
        {
          "rank": 11,
          "name": "兆豐",
          "buy": 925,
          "sell": 716,
          "net": 209
        },
        {
          "rank": 12,
          "name": "華南永昌",
          "buy": 852,
          "sell": 745,
          "net": 107
        },
        {
          "rank": 13,
          "name": "星洲瑞銀",
          "buy": 767,
          "sell": 664,
          "net": 103
        },
        {
          "rank": 14,
          "name": "玉山證券",
          "buy": 621,
          "sell": 562,
          "net": 59
        },
        {
          "rank": 15,
          "name": "合庫",
          "buy": 386,
          "sell": 379,
          "net": 7
        }
      ],
      "total_net": -35
    },
    {
      "rank": 10,
      "name": "中美晶",
      "code": "5483",
      "brokers": [
        {
          "rank": 1,
          "name": "元大",
          "buy": 4840,
          "sell": 6429,
          "net": -1589
        },
        {
          "rank": 2,
          "name": "凱基",
          "buy": 2790,
          "sell": 2649,
          "net": 141
        },
        {
          "rank": 3,
          "name": "富邦",
          "buy": 1503,
          "sell": 1779,
          "net": -276
        },
        {
          "rank": 4,
          "name": "永豐金",
          "buy": 1040,
          "sell": 1997,
          "net": -957
        },
        {
          "rank": 5,
          "name": "台新",
          "buy": 1287,
          "sell": 1415,
          "net": -128
        },
        {
          "rank": 6,
          "name": "中國信託證",
          "buy": 1946,
          "sell": 414,
          "net": 1532
        },
        {
          "rank": 7,
          "name": "群益",
          "buy": 1029,
          "sell": 1172,
          "net": -143
        },
        {
          "rank": 8,
          "name": "國泰綜合",
          "buy": 1061,
          "sell": 1091,
          "net": -30
        },
        {
          "rank": 9,
          "name": "統一",
          "buy": 886,
          "sell": 1044,
          "net": -158
        },
        {
          "rank": 10,
          "name": "星洲瑞銀",
          "buy": 1282,
          "sell": 395,
          "net": 887
        },
        {
          "rank": 11,
          "name": "美商高盛亞",
          "buy": 1003,
          "sell": 586,
          "net": 417
        },
        {
          "rank": 12,
          "name": "兆豐",
          "buy": 739,
          "sell": 458,
          "net": 281
        },
        {
          "rank": 13,
          "name": "華南永昌",
          "buy": 495,
          "sell": 634,
          "net": -139
        },
        {
          "rank": 14,
          "name": "國票",
          "buy": 507,
          "sell": 596,
          "net": -89
        },
        {
          "rank": 15,
          "name": "玉山證券",
          "buy": 372,
          "sell": 704,
          "net": -332
        }
      ],
      "total_net": -583
    },
    {
      "rank": 11,
      "name": "聯光通",
      "code": "4903",
      "brokers": [
        {
          "rank": 1,
          "name": "元大",
          "buy": 6123,
          "sell": 5458,
          "net": 665
        },
        {
          "rank": 2,
          "name": "凱基",
          "buy": 2575,
          "sell": 2783,
          "net": -208
        },
        {
          "rank": 3,
          "name": "富邦",
          "buy": 2075,
          "sell": 1899,
          "net": 176
        },
        {
          "rank": 4,
          "name": "永豐金",
          "buy": 1872,
          "sell": 1498,
          "net": 374
        },
        {
          "rank": 5,
          "name": "群益",
          "buy": 1648,
          "sell": 1667,
          "net": -19
        },
        {
          "rank": 6,
          "name": "台新",
          "buy": 1752,
          "sell": 1345,
          "net": 407
        },
        {
          "rank": 7,
          "name": "華南永昌",
          "buy": 998,
          "sell": 981,
          "net": 17
        },
        {
          "rank": 8,
          "name": "星洲瑞銀",
          "buy": 467,
          "sell": 1233,
          "net": -766
        },
        {
          "rank": 9,
          "name": "統一",
          "buy": 779,
          "sell": 916,
          "net": -137
        },
        {
          "rank": 10,
          "name": "兆豐",
          "buy": 715,
          "sell": 939,
          "net": -224
        },
        {
          "rank": 11,
          "name": "玉山證券",
          "buy": 646,
          "sell": 545,
          "net": 101
        },
        {
          "rank": 12,
          "name": "新光",
          "buy": 581,
          "sell": 496,
          "net": 85
        },
        {
          "rank": 13,
          "name": "美商高盛亞",
          "buy": 440,
          "sell": 538,
          "net": -98
        },
        {
          "rank": 14,
          "name": "美林證券",
          "buy": 227,
          "sell": 647,
          "net": -420
        },
        {
          "rank": 15,
          "name": "摩根大通",
          "buy": 175,
          "sell": 648,
          "net": -473
        }
      ],
      "total_net": -520
    },
    {
      "rank": 12,
      "name": "台嘉碩",
      "code": "3221",
      "brokers": [
        {
          "rank": 1,
          "name": "元大",
          "buy": 3752,
          "sell": 3646,
          "net": 106
        },
        {
          "rank": 2,
          "name": "凱基",
          "buy": 2100,
          "sell": 3134,
          "net": -1034
        },
        {
          "rank": 3,
          "name": "富邦",
          "buy": 3084,
          "sell": 2084,
          "net": 1000
        },
        {
          "rank": 4,
          "name": "國泰綜合",
          "buy": 1404,
          "sell": 1205,
          "net": 199
        },
        {
          "rank": 5,
          "name": "統一",
          "buy": 1512,
          "sell": 621,
          "net": 891
        },
        {
          "rank": 6,
          "name": "永豐金",
          "buy": 749,
          "sell": 1238,
          "net": -489
        },
        {
          "rank": 7,
          "name": "台新",
          "buy": 873,
          "sell": 1107,
          "net": -234
        },
        {
          "rank": 8,
          "name": "群益",
          "buy": 654,
          "sell": 964,
          "net": -310
        },
        {
          "rank": 9,
          "name": "國票",
          "buy": 917,
          "sell": 605,
          "net": 312
        },
        {
          "rank": 10,
          "name": "華南永昌",
          "buy": 623,
          "sell": 657,
          "net": -34
        },
        {
          "rank": 11,
          "name": "兆豐",
          "buy": 381,
          "sell": 375,
          "net": 6
        },
        {
          "rank": 12,
          "name": "新光",
          "buy": 312,
          "sell": 419,
          "net": -107
        },
        {
          "rank": 13,
          "name": "玉山證券",
          "buy": 376,
          "sell": 304,
          "net": 72
        },
        {
          "rank": 14,
          "name": "星洲瑞銀",
          "buy": 215,
          "sell": 419,
          "net": -204
        },
        {
          "rank": 15,
          "name": "摩根大通",
          "buy": 454,
          "sell": 67,
          "net": 387
        }
      ],
      "total_net": 561
    },
    {
      "rank": 13,
      "name": "頎邦",
      "code": "6147",
      "brokers": [
        {
          "rank": 1,
          "name": "富邦",
          "buy": 4119,
          "sell": 2348,
          "net": 1771
        },
        {
          "rank": 2,
          "name": "凱基",
          "buy": 2018,
          "sell": 2672,
          "net": -654
        },
        {
          "rank": 3,
          "name": "元大",
          "buy": 1736,
          "sell": 1915,
          "net": -179
        },
        {
          "rank": 4,
          "name": "美林證券",
          "buy": 2760,
          "sell": 657,
          "net": 2103
        },
        {
          "rank": 5,
          "name": "永豐金",
          "buy": 1231,
          "sell": 1625,
          "net": -394
        },
        {
          "rank": 6,
          "name": "摩根士丹利",
          "buy": 796,
          "sell": 1244,
          "net": -448
        },
        {
          "rank": 7,
          "name": "統一",
          "buy": 576,
          "sell": 982,
          "net": -406
        },
        {
          "rank": 8,
          "name": "群益",
          "buy": 707,
          "sell": 727,
          "net": -20
        },
        {
          "rank": 9,
          "name": "台新",
          "buy": 590,
          "sell": 742,
          "net": -152
        },
        {
          "rank": 10,
          "name": "國泰綜合",
          "buy": 633,
          "sell": 470,
          "net": 163
        },
        {
          "rank": 11,
          "name": "摩根大通",
          "buy": 126,
          "sell": 975,
          "net": -849
        },
        {
          "rank": 12,
          "name": "兆豐",
          "buy": 430,
          "sell": 606,
          "net": -176
        },
        {
          "rank": 13,
          "name": "大和國泰",
          "buy": 0,
          "sell": 874,
          "net": -874
        },
        {
          "rank": 14,
          "name": "國票",
          "buy": 324,
          "sell": 389,
          "net": -65
        },
        {
          "rank": 15,
          "name": "華南永昌",
          "buy": 238,
          "sell": 388,
          "net": -150
        }
      ],
      "total_net": -330
    },
    {
      "rank": 14,
      "name": "精材",
      "code": "3374",
      "brokers": [
        {
          "rank": 1,
          "name": "元大",
          "buy": 4264,
          "sell": 3358,
          "net": 906
        },
        {
          "rank": 2,
          "name": "凱基",
          "buy": 2181,
          "sell": 2211,
          "net": -30
        },
        {
          "rank": 3,
          "name": "富邦",
          "buy": 1743,
          "sell": 1092,
          "net": 651
        },
        {
          "rank": 4,
          "name": "台新",
          "buy": 1107,
          "sell": 1330,
          "net": -223
        },
        {
          "rank": 5,
          "name": "國泰綜合",
          "buy": 1282,
          "sell": 717,
          "net": 565
        },
        {
          "rank": 6,
          "name": "永豐金",
          "buy": 1160,
          "sell": 803,
          "net": 357
        },
        {
          "rank": 7,
          "name": "美商高盛亞",
          "buy": 146,
          "sell": 1308,
          "net": -1162
        },
        {
          "rank": 8,
          "name": "群益",
          "buy": 770,
          "sell": 645,
          "net": 125
        },
        {
          "rank": 9,
          "name": "星洲瑞銀",
          "buy": 184,
          "sell": 1147,
          "net": -963
        },
        {
          "rank": 10,
          "name": "玉山證券",
          "buy": 733,
          "sell": 397,
          "net": 336
        },
        {
          "rank": 11,
          "name": "摩根士丹利",
          "buy": 21,
          "sell": 1024,
          "net": -1003
        },
        {
          "rank": 12,
          "name": "華南永昌",
          "buy": 643,
          "sell": 377,
          "net": 266
        },
        {
          "rank": 13,
          "name": "兆豐",
          "buy": 630,
          "sell": 369,
          "net": 261
        },
        {
          "rank": 14,
          "name": "統一",
          "buy": 471,
          "sell": 514,
          "net": -43
        },
        {
          "rank": 15,
          "name": "新光",
          "buy": 545,
          "sell": 349,
          "net": 196
        }
      ],
      "total_net": 239
    },
    {
      "rank": 15,
      "name": "東捷",
      "code": "8064",
      "brokers": [
        {
          "rank": 1,
          "name": "元大",
          "buy": 3856,
          "sell": 3599,
          "net": 257
        },
        {
          "rank": 2,
          "name": "凱基",
          "buy": 2290,
          "sell": 2911,
          "net": -621
        },
        {
          "rank": 3,
          "name": "富邦",
          "buy": 1184,
          "sell": 1499,
          "net": -315
        },
        {
          "rank": 4,
          "name": "永豐金",
          "buy": 1214,
          "sell": 1204,
          "net": 10
        },
        {
          "rank": 5,
          "name": "群益",
          "buy": 1253,
          "sell": 947,
          "net": 306
        },
        {
          "rank": 6,
          "name": "星洲瑞銀",
          "buy": 753,
          "sell": 1300,
          "net": -547
        },
        {
          "rank": 7,
          "name": "台新",
          "buy": 1117,
          "sell": 849,
          "net": 268
        },
        {
          "rank": 8,
          "name": "國泰綜合",
          "buy": 1055,
          "sell": 801,
          "net": 254
        },
        {
          "rank": 9,
          "name": "兆豐",
          "buy": 1107,
          "sell": 304,
          "net": 803
        },
        {
          "rank": 10,
          "name": "統一",
          "buy": 544,
          "sell": 700,
          "net": -156
        },
        {
          "rank": 11,
          "name": "華南永昌",
          "buy": 516,
          "sell": 442,
          "net": 74
        },
        {
          "rank": 12,
          "name": "摩根士丹利",
          "buy": 99,
          "sell": 683,
          "net": -584
        },
        {
          "rank": 13,
          "name": "新光",
          "buy": 444,
          "sell": 308,
          "net": 136
        },
        {
          "rank": 14,
          "name": "玉山證券",
          "buy": 335,
          "sell": 288,
          "net": 47
        },
        {
          "rank": 15,
          "name": "摩根大通",
          "buy": 338,
          "sell": 266,
          "net": 72
        }
      ],
      "total_net": 4
    },
    {
      "rank": 16,
      "name": "鈺創",
      "code": "5351",
      "brokers": [
        {
          "rank": 1,
          "name": "元大",
          "buy": 3221,
          "sell": 3528,
          "net": -307
        },
        {
          "rank": 2,
          "name": "凱基",
          "buy": 1817,
          "sell": 2457,
          "net": -640
        },
        {
          "rank": 3,
          "name": "富邦",
          "buy": 1348,
          "sell": 1374,
          "net": -26
        },
        {
          "rank": 4,
          "name": "台新",
          "buy": 959,
          "sell": 1260,
          "net": -301
        },
        {
          "rank": 5,
          "name": "群益",
          "buy": 1052,
          "sell": 972,
          "net": 80
        },
        {
          "rank": 6,
          "name": "國泰綜合",
          "buy": 953,
          "sell": 992,
          "net": -39
        },
        {
          "rank": 7,
          "name": "永豐金",
          "buy": 897,
          "sell": 702,
          "net": 195
        },
        {
          "rank": 8,
          "name": "摩根士丹利",
          "buy": 956,
          "sell": 580,
          "net": 376
        },
        {
          "rank": 9,
          "name": "華南永昌",
          "buy": 637,
          "sell": 507,
          "net": 130
        },
        {
          "rank": 10,
          "name": "美商高盛亞",
          "buy": 404,
          "sell": 675,
          "net": -271
        },
        {
          "rank": 11,
          "name": "兆豐",
          "buy": 477,
          "sell": 568,
          "net": -91
        },
        {
          "rank": 12,
          "name": "星洲瑞銀",
          "buy": 789,
          "sell": 219,
          "net": 570
        },
        {
          "rank": 13,
          "name": "玉山證券",
          "buy": 492,
          "sell": 441,
          "net": 51
        },
        {
          "rank": 14,
          "name": "美林證券",
          "buy": 509,
          "sell": 391,
          "net": 118
        },
        {
          "rank": 15,
          "name": "摩根大通",
          "buy": 539,
          "sell": 274,
          "net": 265
        }
      ],
      "total_net": 110
    },
    {
      "rank": 17,
      "name": "欣銓",
      "code": "3264",
      "brokers": [
        {
          "rank": 1,
          "name": "元大",
          "buy": 5987,
          "sell": 4043,
          "net": 1944
        },
        {
          "rank": 2,
          "name": "凱基",
          "buy": 2371,
          "sell": 2491,
          "net": -120
        },
        {
          "rank": 3,
          "name": "富邦",
          "buy": 818,
          "sell": 1428,
          "net": -610
        },
        {
          "rank": 4,
          "name": "永豐金",
          "buy": 711,
          "sell": 682,
          "net": 29
        },
        {
          "rank": 5,
          "name": "國泰綜合",
          "buy": 429,
          "sell": 840,
          "net": -411
        },
        {
          "rank": 6,
          "name": "群益",
          "buy": 554,
          "sell": 630,
          "net": -76
        },
        {
          "rank": 7,
          "name": "台新",
          "buy": 352,
          "sell": 707,
          "net": -355
        },
        {
          "rank": 8,
          "name": "美商高盛亞",
          "buy": 450,
          "sell": 435,
          "net": 15
        },
        {
          "rank": 9,
          "name": "中國信託證",
          "buy": 612,
          "sell": 206,
          "net": 406
        },
        {
          "rank": 10,
          "name": "華南永昌",
          "buy": 196,
          "sell": 612,
          "net": -416
        },
        {
          "rank": 11,
          "name": "統一",
          "buy": 310,
          "sell": 476,
          "net": -166
        },
        {
          "rank": 12,
          "name": "港商野村",
          "buy": 769,
          "sell": 8,
          "net": 761
        },
        {
          "rank": 13,
          "name": "新光",
          "buy": 199,
          "sell": 483,
          "net": -284
        },
        {
          "rank": 14,
          "name": "兆豐",
          "buy": 119,
          "sell": 520,
          "net": -401
        },
        {
          "rank": 15,
          "name": "摩根大通",
          "buy": 518,
          "sell": 43,
          "net": 475
        }
      ],
      "total_net": 791
    },
    {
      "rank": 18,
      "name": "良維",
      "code": "6290",
      "brokers": [
        {
          "rank": 1,
          "name": "元大",
          "buy": 3458,
          "sell": 3028,
          "net": 430
        },
        {
          "rank": 2,
          "name": "凱基",
          "buy": 2183,
          "sell": 3505,
          "net": -1322
        },
        {
          "rank": 3,
          "name": "富邦",
          "buy": 1582,
          "sell": 712,
          "net": 870
        },
        {
          "rank": 4,
          "name": "群益",
          "buy": 819,
          "sell": 918,
          "net": -99
        },
        {
          "rank": 5,
          "name": "台新",
          "buy": 914,
          "sell": 766,
          "net": 148
        },
        {
          "rank": 6,
          "name": "摩根士丹利",
          "buy": 837,
          "sell": 689,
          "net": 148
        },
        {
          "rank": 7,
          "name": "永豐金",
          "buy": 614,
          "sell": 828,
          "net": -214
        },
        {
          "rank": 8,
          "name": "國泰綜合",
          "buy": 721,
          "sell": 594,
          "net": 127
        },
        {
          "rank": 9,
          "name": "美商高盛亞",
          "buy": 397,
          "sell": 653,
          "net": -256
        },
        {
          "rank": 10,
          "name": "統一",
          "buy": 557,
          "sell": 459,
          "net": 98
        },
        {
          "rank": 11,
          "name": "華南永昌",
          "buy": 475,
          "sell": 339,
          "net": 136
        },
        {
          "rank": 12,
          "name": "摩根大通",
          "buy": 398,
          "sell": 393,
          "net": 5
        },
        {
          "rank": 13,
          "name": "兆豐",
          "buy": 494,
          "sell": 221,
          "net": 273
        },
        {
          "rank": 14,
          "name": "星洲瑞銀",
          "buy": 239,
          "sell": 412,
          "net": -173
        },
        {
          "rank": 15,
          "name": "玉山證券",
          "buy": 299,
          "sell": 261,
          "net": 38
        }
      ],
      "total_net": 209
    },
    {
      "rank": 19,
      "name": "華電網",
      "code": "6163",
      "brokers": [
        {
          "rank": 1,
          "name": "元大",
          "buy": 3209,
          "sell": 2255,
          "net": 954
        },
        {
          "rank": 2,
          "name": "凱基",
          "buy": 1627,
          "sell": 2105,
          "net": -478
        },
        {
          "rank": 3,
          "name": "富邦",
          "buy": 1280,
          "sell": 922,
          "net": 358
        },
        {
          "rank": 4,
          "name": "永豐金",
          "buy": 930,
          "sell": 870,
          "net": 60
        },
        {
          "rank": 5,
          "name": "國泰綜合",
          "buy": 1020,
          "sell": 646,
          "net": 374
        },
        {
          "rank": 6,
          "name": "摩根士丹利",
          "buy": 273,
          "sell": 1216,
          "net": -943
        },
        {
          "rank": 7,
          "name": "台新",
          "buy": 842,
          "sell": 490,
          "net": 352
        },
        {
          "rank": 8,
          "name": "群益",
          "buy": 754,
          "sell": 564,
          "net": 190
        },
        {
          "rank": 9,
          "name": "統一",
          "buy": 447,
          "sell": 813,
          "net": -366
        },
        {
          "rank": 10,
          "name": "美林證券",
          "buy": 142,
          "sell": 757,
          "net": -615
        },
        {
          "rank": 11,
          "name": "國票",
          "buy": 404,
          "sell": 449,
          "net": -45
        },
        {
          "rank": 12,
          "name": "美商高盛亞",
          "buy": 292,
          "sell": 546,
          "net": -254
        },
        {
          "rank": 13,
          "name": "玉山證券",
          "buy": 343,
          "sell": 327,
          "net": 16
        },
        {
          "rank": 14,
          "name": "第一金證券",
          "buy": 349,
          "sell": 289,
          "net": 60
        },
        {
          "rank": 15,
          "name": "華南永昌",
          "buy": 390,
          "sell": 235,
          "net": 155
        }
      ],
      "total_net": -182
    },
    {
      "rank": 20,
      "name": "環球晶",
      "code": "6488",
      "brokers": [
        {
          "rank": 1,
          "name": "元大",
          "buy": 2771,
          "sell": 2968,
          "net": -197
        },
        {
          "rank": 2,
          "name": "凱基",
          "buy": 1481,
          "sell": 1903,
          "net": -422
        },
        {
          "rank": 3,
          "name": "富邦",
          "buy": 1291,
          "sell": 1149,
          "net": 142
        },
        {
          "rank": 4,
          "name": "台新",
          "buy": 685,
          "sell": 796,
          "net": -111
        },
        {
          "rank": 5,
          "name": "國泰綜合",
          "buy": 959,
          "sell": 463,
          "net": 496
        },
        {
          "rank": 6,
          "name": "永豐金",
          "buy": 697,
          "sell": 723,
          "net": -26
        },
        {
          "rank": 7,
          "name": "群益",
          "buy": 667,
          "sell": 569,
          "net": 98
        },
        {
          "rank": 8,
          "name": "摩根士丹利",
          "buy": 834,
          "sell": 345,
          "net": 489
        },
        {
          "rank": 9,
          "name": "合庫",
          "buy": 60,
          "sell": 857,
          "net": -797
        },
        {
          "rank": 10,
          "name": "國票",
          "buy": 472,
          "sell": 410,
          "net": 62
        },
        {
          "rank": 11,
          "name": "兆豐",
          "buy": 322,
          "sell": 432,
          "net": -110
        },
        {
          "rank": 12,
          "name": "美林證券",
          "buy": 400,
          "sell": 250,
          "net": 150
        },
        {
          "rank": 13,
          "name": "美商高盛亞",
          "buy": 218,
          "sell": 426,
          "net": -208
        },
        {
          "rank": 14,
          "name": "統一",
          "buy": 272,
          "sell": 336,
          "net": -64
        },
        {
          "rank": 15,
          "name": "玉山證券",
          "buy": 266,
          "sell": 323,
          "net": -57
        }
      ],
      "total_net": -555
    },
    {
      "rank": 21,
      "name": "泰藝",
      "code": "8289",
      "brokers": [
        {
          "rank": 1,
          "name": "元大",
          "buy": 2275,
          "sell": 2228,
          "net": 47
        },
        {
          "rank": 2,
          "name": "富邦",
          "buy": 1760,
          "sell": 1365,
          "net": 395
        },
        {
          "rank": 3,
          "name": "凱基",
          "buy": 1267,
          "sell": 1424,
          "net": -157
        },
        {
          "rank": 4,
          "name": "永豐金",
          "buy": 1105,
          "sell": 1093,
          "net": 12
        },
        {
          "rank": 5,
          "name": "台新",
          "buy": 981,
          "sell": 678,
          "net": 303
        },
        {
          "rank": 6,
          "name": "華南永昌",
          "buy": 685,
          "sell": 803,
          "net": -118
        },
        {
          "rank": 7,
          "name": "國泰綜合",
          "buy": 822,
          "sell": 541,
          "net": 281
        },
        {
          "rank": 8,
          "name": "群益",
          "buy": 598,
          "sell": 579,
          "net": 19
        },
        {
          "rank": 9,
          "name": "玉山證券",
          "buy": 526,
          "sell": 471,
          "net": 55
        },
        {
          "rank": 10,
          "name": "統一",
          "buy": 468,
          "sell": 528,
          "net": -60
        },
        {
          "rank": 11,
          "name": "摩根大通",
          "buy": 242,
          "sell": 372,
          "net": -130
        },
        {
          "rank": 12,
          "name": "兆豐",
          "buy": 260,
          "sell": 343,
          "net": -83
        },
        {
          "rank": 13,
          "name": "康和",
          "buy": 66,
          "sell": 507,
          "net": -441
        },
        {
          "rank": 14,
          "name": "美林證券",
          "buy": 55,
          "sell": 359,
          "net": -304
        },
        {
          "rank": 15,
          "name": "新光",
          "buy": 213,
          "sell": 197,
          "net": 16
        }
      ],
      "total_net": -165
    },
    {
      "rank": 22,
      "name": "均豪",
      "code": "5443",
      "brokers": [
        {
          "rank": 1,
          "name": "元大",
          "buy": 2947,
          "sell": 2266,
          "net": 681
        },
        {
          "rank": 2,
          "name": "凱基",
          "buy": 1419,
          "sell": 1694,
          "net": -275
        },
        {
          "rank": 3,
          "name": "富邦",
          "buy": 929,
          "sell": 1454,
          "net": -525
        },
        {
          "rank": 4,
          "name": "永豐金",
          "buy": 704,
          "sell": 800,
          "net": -96
        },
        {
          "rank": 5,
          "name": "群益",
          "buy": 720,
          "sell": 552,
          "net": 168
        },
        {
          "rank": 6,
          "name": "台新",
          "buy": 709,
          "sell": 420,
          "net": 289
        },
        {
          "rank": 7,
          "name": "國泰綜合",
          "buy": 605,
          "sell": 481,
          "net": 124
        },
        {
          "rank": 8,
          "name": "玉山證券",
          "buy": 817,
          "sell": 230,
          "net": 587
        },
        {
          "rank": 9,
          "name": "中國信託證",
          "buy": 394,
          "sell": 469,
          "net": -75
        },
        {
          "rank": 10,
          "name": "統一",
          "buy": 418,
          "sell": 415,
          "net": 3
        },
        {
          "rank": 11,
          "name": "美商高盛亞",
          "buy": 306,
          "sell": 476,
          "net": -170
        },
        {
          "rank": 12,
          "name": "星洲瑞銀",
          "buy": 253,
          "sell": 482,
          "net": -229
        },
        {
          "rank": 13,
          "name": "華南永昌",
          "buy": 469,
          "sell": 215,
          "net": 254
        },
        {
          "rank": 14,
          "name": "兆豐",
          "buy": 310,
          "sell": 276,
          "net": 34
        },
        {
          "rank": 15,
          "name": "第一金證券",
          "buy": 321,
          "sell": 213,
          "net": 108
        }
      ],
      "total_net": 878
    },
    {
      "rank": 23,
      "name": "易發",
      "code": "6425",
      "brokers": [
        {
          "rank": 1,
          "name": "元大",
          "buy": 2693,
          "sell": 2702,
          "net": -9
        },
        {
          "rank": 2,
          "name": "凱基",
          "buy": 1506,
          "sell": 1711,
          "net": -205
        },
        {
          "rank": 3,
          "name": "富邦",
          "buy": 1109,
          "sell": 954,
          "net": 155
        },
        {
          "rank": 4,
          "name": "永豐金",
          "buy": 999,
          "sell": 988,
          "net": 11
        },
        {
          "rank": 5,
          "name": "群益",
          "buy": 718,
          "sell": 580,
          "net": 138
        },
        {
          "rank": 6,
          "name": "台新",
          "buy": 621,
          "sell": 656,
          "net": -35
        },
        {
          "rank": 7,
          "name": "國泰綜合",
          "buy": 556,
          "sell": 640,
          "net": -84
        },
        {
          "rank": 8,
          "name": "玉山證券",
          "buy": 508,
          "sell": 496,
          "net": 12
        },
        {
          "rank": 9,
          "name": "華南永昌",
          "buy": 438,
          "sell": 414,
          "net": 24
        },
        {
          "rank": 10,
          "name": "兆豐",
          "buy": 459,
          "sell": 345,
          "net": 114
        },
        {
          "rank": 11,
          "name": "統一",
          "buy": 462,
          "sell": 335,
          "net": 127
        },
        {
          "rank": 12,
          "name": "國票",
          "buy": 282,
          "sell": 287,
          "net": -5
        },
        {
          "rank": 13,
          "name": "中國信託證",
          "buy": 242,
          "sell": 322,
          "net": -80
        },
        {
          "rank": 14,
          "name": "第一金證券",
          "buy": 297,
          "sell": 240,
          "net": 57
        },
        {
          "rank": 15,
          "name": "星洲瑞銀",
          "buy": 251,
          "sell": 251,
          "net": 0
        }
      ],
      "total_net": 220
    },
    {
      "rank": 24,
      "name": "九豪",
      "code": "6127",
      "brokers": [
        {
          "rank": 1,
          "name": "元大",
          "buy": 2970,
          "sell": 2612,
          "net": 358
        },
        {
          "rank": 2,
          "name": "凱基",
          "buy": 1374,
          "sell": 1445,
          "net": -71
        },
        {
          "rank": 3,
          "name": "富邦",
          "buy": 1606,
          "sell": 843,
          "net": 763
        },
        {
          "rank": 4,
          "name": "永豐金",
          "buy": 543,
          "sell": 1364,
          "net": -821
        },
        {
          "rank": 5,
          "name": "台新",
          "buy": 616,
          "sell": 726,
          "net": -110
        },
        {
          "rank": 6,
          "name": "國泰綜合",
          "buy": 596,
          "sell": 704,
          "net": -108
        },
        {
          "rank": 7,
          "name": "群益",
          "buy": 582,
          "sell": 642,
          "net": -60
        },
        {
          "rank": 8,
          "name": "華南永昌",
          "buy": 409,
          "sell": 528,
          "net": -119
        },
        {
          "rank": 9,
          "name": "摩根大通",
          "buy": 444,
          "sell": 226,
          "net": 218
        },
        {
          "rank": 10,
          "name": "美商高盛亞",
          "buy": 352,
          "sell": 277,
          "net": 75
        },
        {
          "rank": 11,
          "name": "玉山證券",
          "buy": 262,
          "sell": 366,
          "net": -104
        },
        {
          "rank": 12,
          "name": "兆豐",
          "buy": 291,
          "sell": 331,
          "net": -40
        },
        {
          "rank": 13,
          "name": "新光",
          "buy": 202,
          "sell": 249,
          "net": -47
        },
        {
          "rank": 14,
          "name": "星洲瑞銀",
          "buy": 320,
          "sell": 114,
          "net": 206
        },
        {
          "rank": 15,
          "name": "統一",
          "buy": 188,
          "sell": 236,
          "net": -48
        }
      ],
      "total_net": 92
    },
    {
      "rank": 25,
      "name": "長科*",
      "code": "6548",
      "brokers": [
        {
          "rank": 1,
          "name": "元大",
          "buy": 2275,
          "sell": 2369,
          "net": -94
        },
        {
          "rank": 2,
          "name": "凱基",
          "buy": 1783,
          "sell": 1520,
          "net": 263
        },
        {
          "rank": 3,
          "name": "富邦",
          "buy": 904,
          "sell": 855,
          "net": 49
        },
        {
          "rank": 4,
          "name": "國泰綜合",
          "buy": 737,
          "sell": 738,
          "net": -1
        },
        {
          "rank": 5,
          "name": "永豐金",
          "buy": 606,
          "sell": 617,
          "net": -11
        },
        {
          "rank": 6,
          "name": "群益",
          "buy": 596,
          "sell": 554,
          "net": 42
        },
        {
          "rank": 7,
          "name": "華南永昌",
          "buy": 540,
          "sell": 589,
          "net": -49
        },
        {
          "rank": 8,
          "name": "台新",
          "buy": 536,
          "sell": 588,
          "net": -52
        },
        {
          "rank": 9,
          "name": "摩根士丹利",
          "buy": 377,
          "sell": 673,
          "net": -296
        },
        {
          "rank": 10,
          "name": "兆豐",
          "buy": 312,
          "sell": 426,
          "net": -114
        },
        {
          "rank": 11,
          "name": "美商高盛亞",
          "buy": 236,
          "sell": 401,
          "net": -165
        },
        {
          "rank": 12,
          "name": "玉山證券",
          "buy": 380,
          "sell": 250,
          "net": 130
        },
        {
          "rank": 13,
          "name": "統一",
          "buy": 232,
          "sell": 377,
          "net": -145
        },
        {
          "rank": 14,
          "name": "國票",
          "buy": 302,
          "sell": 216,
          "net": 86
        },
        {
          "rank": 15,
          "name": "新光",
          "buy": 200,
          "sell": 252,
          "net": -52
        }
      ],
      "total_net": -409
    },
    {
      "rank": 26,
      "name": "磐亞",
      "code": "4707",
      "brokers": [
        {
          "rank": 1,
          "name": "元大",
          "buy": 2667,
          "sell": 2340,
          "net": 327
        },
        {
          "rank": 2,
          "name": "凱基",
          "buy": 1253,
          "sell": 1630,
          "net": -377
        },
        {
          "rank": 3,
          "name": "台新",
          "buy": 825,
          "sell": 975,
          "net": -150
        },
        {
          "rank": 4,
          "name": "富邦",
          "buy": 388,
          "sell": 1233,
          "net": -845
        },
        {
          "rank": 5,
          "name": "台中銀證券",
          "buy": 1459,
          "sell": 88,
          "net": 1371
        },
        {
          "rank": 6,
          "name": "群益",
          "buy": 645,
          "sell": 451,
          "net": 194
        },
        {
          "rank": 7,
          "name": "國泰綜合",
          "buy": 359,
          "sell": 608,
          "net": -249
        },
        {
          "rank": 8,
          "name": "統一",
          "buy": 845,
          "sell": 92,
          "net": 753
        },
        {
          "rank": 9,
          "name": "永豐金",
          "buy": 338,
          "sell": 501,
          "net": -163
        },
        {
          "rank": 10,
          "name": "華南永昌",
          "buy": 289,
          "sell": 304,
          "net": -15
        },
        {
          "rank": 11,
          "name": "摩根大通",
          "buy": 81,
          "sell": 430,
          "net": -349
        },
        {
          "rank": 12,
          "name": "星洲瑞銀",
          "buy": 97,
          "sell": 324,
          "net": -227
        },
        {
          "rank": 13,
          "name": "兆豐",
          "buy": 184,
          "sell": 225,
          "net": -41
        },
        {
          "rank": 14,
          "name": "康和",
          "buy": 123,
          "sell": 229,
          "net": -106
        },
        {
          "rank": 15,
          "name": "玉山證券",
          "buy": 179,
          "sell": 172,
          "net": 7
        }
      ],
      "total_net": 130
    },
    {
      "rank": 27,
      "name": "久元",
      "code": "6261",
      "brokers": [
        {
          "rank": 1,
          "name": "元大",
          "buy": 2087,
          "sell": 2318,
          "net": -231
        },
        {
          "rank": 2,
          "name": "凱基",
          "buy": 944,
          "sell": 1397,
          "net": -453
        },
        {
          "rank": 3,
          "name": "永豐金",
          "buy": 1005,
          "sell": 800,
          "net": 205
        },
        {
          "rank": 4,
          "name": "富邦",
          "buy": 1104,
          "sell": 691,
          "net": 413
        },
        {
          "rank": 5,
          "name": "台新",
          "buy": 706,
          "sell": 583,
          "net": 123
        },
        {
          "rank": 6,
          "name": "宏遠",
          "buy": 1091,
          "sell": 115,
          "net": 976
        },
        {
          "rank": 7,
          "name": "統一",
          "buy": 459,
          "sell": 517,
          "net": -58
        },
        {
          "rank": 8,
          "name": "國泰綜合",
          "buy": 472,
          "sell": 328,
          "net": 144
        },
        {
          "rank": 9,
          "name": "群益",
          "buy": 336,
          "sell": 403,
          "net": -67
        },
        {
          "rank": 10,
          "name": "兆豐",
          "buy": 224,
          "sell": 418,
          "net": -194
        },
        {
          "rank": 11,
          "name": "華南永昌",
          "buy": 184,
          "sell": 386,
          "net": -202
        },
        {
          "rank": 12,
          "name": "國票",
          "buy": 263,
          "sell": 247,
          "net": 16
        },
        {
          "rank": 13,
          "name": "摩根士丹利",
          "buy": 81,
          "sell": 427,
          "net": -346
        },
        {
          "rank": 14,
          "name": "美商高盛亞",
          "buy": 245,
          "sell": 263,
          "net": -18
        },
        {
          "rank": 15,
          "name": "中國信託證",
          "buy": 350,
          "sell": 94,
          "net": 256
        }
      ],
      "total_net": 564
    },
    {
      "rank": 28,
      "name": "千附",
      "code": "8383",
      "brokers": [
        {
          "rank": 1,
          "name": "元大",
          "buy": 2468,
          "sell": 2964,
          "net": -496
        },
        {
          "rank": 2,
          "name": "凱基",
          "buy": 818,
          "sell": 1070,
          "net": -252
        },
        {
          "rank": 3,
          "name": "富邦",
          "buy": 945,
          "sell": 574,
          "net": 371
        },
        {
          "rank": 4,
          "name": "群益",
          "buy": 737,
          "sell": 551,
          "net": 186
        },
        {
          "rank": 5,
          "name": "台新",
          "buy": 538,
          "sell": 645,
          "net": -107
        },
        {
          "rank": 6,
          "name": "永豐金",
          "buy": 530,
          "sell": 511,
          "net": 19
        },
        {
          "rank": 7,
          "name": "華南永昌",
          "buy": 471,
          "sell": 558,
          "net": -87
        },
        {
          "rank": 8,
          "name": "美商高盛亞",
          "buy": 450,
          "sell": 511,
          "net": -61
        },
        {
          "rank": 9,
          "name": "國泰綜合",
          "buy": 526,
          "sell": 384,
          "net": 142
        },
        {
          "rank": 10,
          "name": "摩根士丹利",
          "buy": 360,
          "sell": 311,
          "net": 49
        },
        {
          "rank": 11,
          "name": "兆豐",
          "buy": 371,
          "sell": 200,
          "net": 171
        },
        {
          "rank": 12,
          "name": "統一",
          "buy": 211,
          "sell": 303,
          "net": -92
        },
        {
          "rank": 13,
          "name": "摩根大通",
          "buy": 103,
          "sell": 370,
          "net": -267
        },
        {
          "rank": 14,
          "name": "星洲瑞銀",
          "buy": 225,
          "sell": 202,
          "net": 23
        },
        {
          "rank": 15,
          "name": "合庫",
          "buy": 222,
          "sell": 185,
          "net": 37
        }
      ],
      "total_net": -364
    },
    {
      "rank": 29,
      "name": "宏捷科",
      "code": "8086",
      "brokers": [
        {
          "rank": 1,
          "name": "元大",
          "buy": 2003,
          "sell": 1851,
          "net": 152
        },
        {
          "rank": 2,
          "name": "凱基",
          "buy": 1737,
          "sell": 1114,
          "net": 623
        },
        {
          "rank": 3,
          "name": "富邦",
          "buy": 684,
          "sell": 695,
          "net": -11
        },
        {
          "rank": 4,
          "name": "台新",
          "buy": 503,
          "sell": 747,
          "net": -244
        },
        {
          "rank": 5,
          "name": "摩根士丹利",
          "buy": 406,
          "sell": 769,
          "net": -363
        },
        {
          "rank": 6,
          "name": "永豐金",
          "buy": 556,
          "sell": 504,
          "net": 52
        },
        {
          "rank": 7,
          "name": "華南永昌",
          "buy": 368,
          "sell": 674,
          "net": -306
        },
        {
          "rank": 8,
          "name": "國泰綜合",
          "buy": 458,
          "sell": 480,
          "net": -22
        },
        {
          "rank": 9,
          "name": "群益",
          "buy": 379,
          "sell": 468,
          "net": -89
        },
        {
          "rank": 10,
          "name": "星洲瑞銀",
          "buy": 554,
          "sell": 247,
          "net": 307
        },
        {
          "rank": 11,
          "name": "統一",
          "buy": 277,
          "sell": 397,
          "net": -120
        },
        {
          "rank": 12,
          "name": "兆豐",
          "buy": 329,
          "sell": 312,
          "net": 17
        },
        {
          "rank": 13,
          "name": "新光",
          "buy": 284,
          "sell": 257,
          "net": 27
        },
        {
          "rank": 14,
          "name": "港商麥格理",
          "buy": 0,
          "sell": 380,
          "net": -380
        },
        {
          "rank": 15,
          "name": "玉山證券",
          "buy": 203,
          "sell": 177,
          "net": 26
        }
      ],
      "total_net": -331
    },
    {
      "rank": 30,
      "name": "高技",
      "code": "5439",
      "brokers": [
        {
          "rank": 1,
          "name": "元大",
          "buy": 3050,
          "sell": 2736,
          "net": 314
        },
        {
          "rank": 2,
          "name": "凱基",
          "buy": 1315,
          "sell": 1508,
          "net": -193
        },
        {
          "rank": 3,
          "name": "富邦",
          "buy": 673,
          "sell": 818,
          "net": -145
        },
        {
          "rank": 4,
          "name": "群益",
          "buy": 549,
          "sell": 549,
          "net": 0
        },
        {
          "rank": 5,
          "name": "永豐金",
          "buy": 496,
          "sell": 515,
          "net": -19
        },
        {
          "rank": 6,
          "name": "國泰綜合",
          "buy": 533,
          "sell": 376,
          "net": 157
        },
        {
          "rank": 7,
          "name": "台新",
          "buy": 502,
          "sell": 393,
          "net": 109
        },
        {
          "rank": 8,
          "name": "摩根士丹利",
          "buy": 88,
          "sell": 662,
          "net": -574
        },
        {
          "rank": 9,
          "name": "統一",
          "buy": 427,
          "sell": 295,
          "net": 132
        },
        {
          "rank": 10,
          "name": "港商野村",
          "buy": 144,
          "sell": 504,
          "net": -360
        },
        {
          "rank": 11,
          "name": "星洲瑞銀",
          "buy": 195,
          "sell": 450,
          "net": -255
        },
        {
          "rank": 12,
          "name": "摩根大通",
          "buy": 284,
          "sell": 309,
          "net": -25
        },
        {
          "rank": 13,
          "name": "兆豐",
          "buy": 420,
          "sell": 130,
          "net": 290
        },
        {
          "rank": 14,
          "name": "玉山證券",
          "buy": 285,
          "sell": 248,
          "net": 37
        },
        {
          "rank": 15,
          "name": "新光",
          "buy": 257,
          "sell": 180,
          "net": 77
        }
      ],
      "total_net": -455
    }
  ]
}