{
  "date": "2026-04-21",
  "unit": "千元",
  "stocks": [
    {
      "rank": 1,
      "name": "穩懋",
      "code": "3105",
      "brokers": [
        {
          "rank": 1,
          "name": "元大",
          "buy": 8283832,
          "sell": 6769420,
          "net": 1514412
        },
        {
          "rank": 2,
          "name": "凱基",
          "buy": 3667506,
          "sell": 4625594,
          "net": -958088
        },
        {
          "rank": 3,
          "name": "國泰綜合",
          "buy": 2374800,
          "sell": 2090972,
          "net": 283828
        },
        {
          "rank": 4,
          "name": "台新",
          "buy": 1975585,
          "sell": 1574021,
          "net": 401564
        },
        {
          "rank": 5,
          "name": "富邦",
          "buy": 1790496,
          "sell": 1749328,
          "net": 41168
        },
        {
          "rank": 6,
          "name": "永豐金",
          "buy": 1627432,
          "sell": 1383162,
          "net": 244270
        },
        {
          "rank": 7,
          "name": "群益",
          "buy": 1379636,
          "sell": 1302101,
          "net": 77535
        },
        {
          "rank": 8,
          "name": "摩根士丹利",
          "buy": 1214773,
          "sell": 1219395,
          "net": -4622
        },
        {
          "rank": 9,
          "name": "摩根大通",
          "buy": 1173665,
          "sell": 1218687,
          "net": -45022
        },
        {
          "rank": 10,
          "name": "星洲瑞銀",
          "buy": 647896,
          "sell": 1298676,
          "net": -650780
        },
        {
          "rank": 11,
          "name": "美商高盛亞",
          "buy": 521326,
          "sell": 1406449,
          "net": -885123
        },
        {
          "rank": 12,
          "name": "統一",
          "buy": 721312,
          "sell": 1137769,
          "net": -416457
        },
        {
          "rank": 13,
          "name": "美林證券",
          "buy": 1081171,
          "sell": 465703,
          "net": 615468
        },
        {
          "rank": 14,
          "name": "玉山證券",
          "buy": 1006819,
          "sell": 463103,
          "net": 543716
        },
        {
          "rank": 15,
          "name": "華南永昌",
          "buy": 714941,
          "sell": 676163,
          "net": 38778
        }
      ],
      "total_net": 800647
    },
    {
      "rank": 2,
      "name": "金居",
      "code": "8358",
      "brokers": [
        {
          "rank": 1,
          "name": "元大",
          "buy": 6258543,
          "sell": 5373876,
          "net": 884667
        },
        {
          "rank": 2,
          "name": "凱基",
          "buy": 2858120,
          "sell": 3061441,
          "net": -203321
        },
        {
          "rank": 3,
          "name": "國泰綜合",
          "buy": 1882040,
          "sell": 1441511,
          "net": 440529
        },
        {
          "rank": 4,
          "name": "富邦",
          "buy": 1391879,
          "sell": 1916072,
          "net": -524193
        },
        {
          "rank": 5,
          "name": "永豐金",
          "buy": 1164742,
          "sell": 1205520,
          "net": -40778
        },
        {
          "rank": 6,
          "name": "群益",
          "buy": 1262409,
          "sell": 964735,
          "net": 297674
        },
        {
          "rank": 7,
          "name": "台新",
          "buy": 1085213,
          "sell": 871794,
          "net": 213419
        },
        {
          "rank": 8,
          "name": "統一",
          "buy": 931902,
          "sell": 889938,
          "net": 41964
        },
        {
          "rank": 9,
          "name": "華南永昌",
          "buy": 662028,
          "sell": 567470,
          "net": 94558
        },
        {
          "rank": 10,
          "name": "星洲瑞銀",
          "buy": 592743,
          "sell": 618770,
          "net": -26027
        },
        {
          "rank": 11,
          "name": "摩根士丹利",
          "buy": 108754,
          "sell": 978710,
          "net": -869956
        },
        {
          "rank": 12,
          "name": "兆豐",
          "buy": 548245,
          "sell": 500822,
          "net": 47423
        },
        {
          "rank": 13,
          "name": "國票",
          "buy": 252110,
          "sell": 673611,
          "net": -421501
        },
        {
          "rank": 14,
          "name": "新光",
          "buy": 525026,
          "sell": 386126,
          "net": 138900
        },
        {
          "rank": 15,
          "name": "玉山證券",
          "buy": 543332,
          "sell": 356224,
          "net": 187108
        }
      ],
      "total_net": 260466
    },
    {
      "rank": 3,
      "name": "群聯",
      "code": "8299",
      "brokers": [
        {
          "rank": 1,
          "name": "元大",
          "buy": 2352150,
          "sell": 3448080,
          "net": -1095930
        },
        {
          "rank": 2,
          "name": "富邦",
          "buy": 1923715,
          "sell": 1633965,
          "net": 289750
        },
        {
          "rank": 3,
          "name": "凱基",
          "buy": 1697270,
          "sell": 1676575,
          "net": 20695
        },
        {
          "rank": 4,
          "name": "永豐金",
          "buy": 1779265,
          "sell": 1441395,
          "net": 337870
        },
        {
          "rank": 5,
          "name": "台新",
          "buy": 1203170,
          "sell": 818835,
          "net": 384335
        },
        {
          "rank": 6,
          "name": "群益",
          "buy": 412365,
          "sell": 657325,
          "net": -244960
        },
        {
          "rank": 7,
          "name": "國泰綜合",
          "buy": 396000,
          "sell": 646425,
          "net": -250425
        },
        {
          "rank": 8,
          "name": "美商高盛亞",
          "buy": 317180,
          "sell": 704300,
          "net": -387120
        },
        {
          "rank": 9,
          "name": "國票",
          "buy": 647490,
          "sell": 326450,
          "net": 321040
        },
        {
          "rank": 10,
          "name": "華南永昌",
          "buy": 465315,
          "sell": 475070,
          "net": -9755
        },
        {
          "rank": 11,
          "name": "統一",
          "buy": 490420,
          "sell": 408755,
          "net": 81665
        },
        {
          "rank": 12,
          "name": "新光",
          "buy": 431365,
          "sell": 429235,
          "net": 2130
        },
        {
          "rank": 13,
          "name": "摩根大通",
          "buy": 626955,
          "sell": 211755,
          "net": 415200
        },
        {
          "rank": 14,
          "name": "玉山證券",
          "buy": 325305,
          "sell": 460415,
          "net": -135110
        },
        {
          "rank": 15,
          "name": "摩根士丹利",
          "buy": 388100,
          "sell": 394630,
          "net": -6530
        }
      ],
      "total_net": -277145
    },
    {
      "rank": 4,
      "name": "威剛",
      "code": "3260",
      "brokers": [
        {
          "rank": 1,
          "name": "元大",
          "buy": 1619335,
          "sell": 2539458,
          "net": -920123
        },
        {
          "rank": 2,
          "name": "凱基",
          "buy": 2080132,
          "sell": 1407923,
          "net": 672209
        },
        {
          "rank": 3,
          "name": "富邦",
          "buy": 1433896,
          "sell": 1173778,
          "net": 260118
        },
        {
          "rank": 4,
          "name": "摩根士丹利",
          "buy": 1237353,
          "sell": 202703,
          "net": 1034650
        },
        {
          "rank": 5,
          "name": "永豐金",
          "buy": 500201,
          "sell": 899028,
          "net": -398827
        },
        {
          "rank": 6,
          "name": "台新",
          "buy": 424089,
          "sell": 873316,
          "net": -449227
        },
        {
          "rank": 7,
          "name": "國泰綜合",
          "buy": 367389,
          "sell": 674871,
          "net": -307482
        },
        {
          "rank": 8,
          "name": "群益",
          "buy": 331271,
          "sell": 646144,
          "net": -314873
        },
        {
          "rank": 9,
          "name": "星洲瑞銀",
          "buy": 790089,
          "sell": 156407,
          "net": 633682
        },
        {
          "rank": 10,
          "name": "港商野村",
          "buy": 849196,
          "sell": 21263,
          "net": 827933
        },
        {
          "rank": 11,
          "name": "華南永昌",
          "buy": 207828,
          "sell": 515631,
          "net": -307803
        },
        {
          "rank": 12,
          "name": "美商高盛亞",
          "buy": 556404,
          "sell": 67927,
          "net": 488477
        },
        {
          "rank": 13,
          "name": "國票",
          "buy": 265039,
          "sell": 326936,
          "net": -61897
        },
        {
          "rank": 14,
          "name": "兆豐",
          "buy": 181216,
          "sell": 366055,
          "net": -184839
        },
        {
          "rank": 15,
          "name": "玉山證券",
          "buy": 160687,
          "sell": 335323,
          "net": -174636
        }
      ],
      "total_net": 797362
    },
    {
      "rank": 5,
      "name": "聯亞",
      "code": "3081",
      "brokers": [
        {
          "rank": 1,
          "name": "元大",
          "buy": 2186775,
          "sell": 2228330,
          "net": -41555
        },
        {
          "rank": 2,
          "name": "凱基",
          "buy": 1207815,
          "sell": 1164785,
          "net": 43030
        },
        {
          "rank": 3,
          "name": "富邦",
          "buy": 881185,
          "sell": 803650,
          "net": 77535
        },
        {
          "rank": 4,
          "name": "台新",
          "buy": 739280,
          "sell": 622655,
          "net": 116625
        },
        {
          "rank": 5,
          "name": "國泰綜合",
          "buy": 609540,
          "sell": 656650,
          "net": -47110
        },
        {
          "rank": 6,
          "name": "永豐金",
          "buy": 574435,
          "sell": 656670,
          "net": -82235
        },
        {
          "rank": 7,
          "name": "美商高盛亞",
          "buy": 678660,
          "sell": 347570,
          "net": 331090
        },
        {
          "rank": 8,
          "name": "星洲瑞銀",
          "buy": 305425,
          "sell": 684085,
          "net": -378660
        },
        {
          "rank": 9,
          "name": "摩根士丹利",
          "buy": 501380,
          "sell": 446090,
          "net": 55290
        },
        {
          "rank": 10,
          "name": "摩根大通",
          "buy": 369320,
          "sell": 548465,
          "net": -179145
        },
        {
          "rank": 11,
          "name": "群益",
          "buy": 490130,
          "sell": 335385,
          "net": 154745
        },
        {
          "rank": 12,
          "name": "新光",
          "buy": 295255,
          "sell": 251475,
          "net": 43780
        },
        {
          "rank": 13,
          "name": "統一",
          "buy": 199160,
          "sell": 338390,
          "net": -139230
        },
        {
          "rank": 14,
          "name": "港商野村",
          "buy": 253795,
          "sell": 277950,
          "net": -24155
        },
        {
          "rank": 15,
          "name": "華南永昌",
          "buy": 228690,
          "sell": 225580,
          "net": 3110
        }
      ],
      "total_net": -66885
    },
    {
      "rank": 6,
      "name": "旺矽",
      "code": "6223",
      "brokers": [
        {
          "rank": 1,
          "name": "元大",
          "buy": 2191435,
          "sell": 1297295,
          "net": 894140
        },
        {
          "rank": 2,
          "name": "星洲瑞銀",
          "buy": 281120,
          "sell": 2855155,
          "net": -2574035
        },
        {
          "rank": 3,
          "name": "凱基",
          "buy": 1724845,
          "sell": 824825,
          "net": 900020
        },
        {
          "rank": 4,
          "name": "美商高盛亞",
          "buy": 794625,
          "sell": 743240,
          "net": 51385
        },
        {
          "rank": 5,
          "name": "國泰綜合",
          "buy": 443790,
          "sell": 644580,
          "net": -200790
        },
        {
          "rank": 6,
          "name": "富邦",
          "buy": 695795,
          "sell": 349195,
          "net": 346600
        },
        {
          "rank": 7,
          "name": "永豐金",
          "buy": 531810,
          "sell": 506980,
          "net": 24830
        },
        {
          "rank": 8,
          "name": "群益",
          "buy": 561245,
          "sell": 423900,
          "net": 137345
        },
        {
          "rank": 9,
          "name": "美林證券",
          "buy": 546645,
          "sell": 115090,
          "net": 431555
        },
        {
          "rank": 10,
          "name": "摩根大通",
          "buy": 295670,
          "sell": 348770,
          "net": -53100
        },
        {
          "rank": 11,
          "name": "台新",
          "buy": 307140,
          "sell": 245145,
          "net": 61995
        },
        {
          "rank": 12,
          "name": "兆豐",
          "buy": 222680,
          "sell": 236085,
          "net": -13405
        },
        {
          "rank": 13,
          "name": "摩根士丹利",
          "buy": 168035,
          "sell": 287480,
          "net": -119445
        },
        {
          "rank": 14,
          "name": "中國信託證",
          "buy": 328835,
          "sell": 63755,
          "net": 265080
        },
        {
          "rank": 15,
          "name": "華南永昌",
          "buy": 172255,
          "sell": 197800,
          "net": -25545
        }
      ],
      "total_net": 126630
    },
    {
      "rank": 7,
      "name": "環球晶",
      "code": "6488",
      "brokers": [
        {
          "rank": 1,
          "name": "元大",
          "buy": 1611739,
          "sell": 1733582,
          "net": -121843
        },
        {
          "rank": 2,
          "name": "凱基",
          "buy": 857829,
          "sell": 1112094,
          "net": -254265
        },
        {
          "rank": 3,
          "name": "富邦",
          "buy": 758059,
          "sell": 666894,
          "net": 91165
        },
        {
          "rank": 4,
          "name": "台新",
          "buy": 400885,
          "sell": 461489,
          "net": -60604
        },
        {
          "rank": 5,
          "name": "國泰綜合",
          "buy": 562968,
          "sell": 270878,
          "net": 292090
        },
        {
          "rank": 6,
          "name": "永豐金",
          "buy": 408254,
          "sell": 424470,
          "net": -16216
        },
        {
          "rank": 7,
          "name": "群益",
          "buy": 386330,
          "sell": 329058,
          "net": 57272
        },
        {
          "rank": 8,
          "name": "摩根士丹利",
          "buy": 491178,
          "sell": 201501,
          "net": 289677
        },
        {
          "rank": 9,
          "name": "合庫",
          "buy": 34468,
          "sell": 497218,
          "net": -462750
        },
        {
          "rank": 10,
          "name": "國票",
          "buy": 279884,
          "sell": 235584,
          "net": 44300
        },
        {
          "rank": 11,
          "name": "兆豐",
          "buy": 186603,
          "sell": 253624,
          "net": -67021
        },
        {
          "rank": 12,
          "name": "美林證券",
          "buy": 231282,
          "sell": 147407,
          "net": 83875
        },
        {
          "rank": 13,
          "name": "美商高盛亞",
          "buy": 125829,
          "sell": 249407,
          "net": -123578
        },
        {
          "rank": 14,
          "name": "統一",
          "buy": 157662,
          "sell": 195073,
          "net": -37411
        },
        {
          "rank": 15,
          "name": "玉山證券",
          "buy": 155925,
          "sell": 187881,
          "net": -31956
        }
      ],
      "total_net": -317265
    },
    {
      "rank": 8,
      "name": "富喬",
      "code": "1815",
      "brokers": [
        {
          "rank": 1,
          "name": "元大",
          "buy": 1640275,
          "sell": 1329682,
          "net": 310593
        },
        {
          "rank": 2,
          "name": "凱基",
          "buy": 710760,
          "sell": 679684,
          "net": 31076
        },
        {
          "rank": 3,
          "name": "富邦",
          "buy": 516254,
          "sell": 605518,
          "net": -89264
        },
        {
          "rank": 4,
          "name": "永豐金",
          "buy": 383191,
          "sell": 424955,
          "net": -41764
        },
        {
          "rank": 5,
          "name": "兆豐",
          "buy": 251491,
          "sell": 504595,
          "net": -253104
        },
        {
          "rank": 6,
          "name": "國泰綜合",
          "buy": 382140,
          "sell": 345172,
          "net": 36968
        },
        {
          "rank": 7,
          "name": "華南永昌",
          "buy": 506732,
          "sell": 191820,
          "net": 314912
        },
        {
          "rank": 8,
          "name": "台新",
          "buy": 347533,
          "sell": 286255,
          "net": 61278
        },
        {
          "rank": 9,
          "name": "統一",
          "buy": 209596,
          "sell": 386187,
          "net": -176591
        },
        {
          "rank": 10,
          "name": "群益",
          "buy": 280586,
          "sell": 196899,
          "net": 83687
        },
        {
          "rank": 11,
          "name": "摩根大通",
          "buy": 183955,
          "sell": 234711,
          "net": -50756
        },
        {
          "rank": 12,
          "name": "玉山證券",
          "buy": 151255,
          "sell": 221168,
          "net": -69913
        },
        {
          "rank": 13,
          "name": "星洲瑞銀",
          "buy": 159987,
          "sell": 199968,
          "net": -39981
        },
        {
          "rank": 14,
          "name": "新光",
          "buy": 154152,
          "sell": 195658,
          "net": -41506
        },
        {
          "rank": 15,
          "name": "美商高盛亞",
          "buy": 67224,
          "sell": 162395,
          "net": -95171
        }
      ],
      "total_net": -19536
    },
    {
      "rank": 9,
      "name": "世界",
      "code": "5347",
      "brokers": [
        {
          "rank": 1,
          "name": "元大",
          "buy": 1546756,
          "sell": 1057023,
          "net": 489733
        },
        {
          "rank": 2,
          "name": "凱基",
          "buy": 673804,
          "sell": 705105,
          "net": -31301
        },
        {
          "rank": 3,
          "name": "富邦",
          "buy": 480655,
          "sell": 463234,
          "net": 17421
        },
        {
          "rank": 4,
          "name": "摩根士丹利",
          "buy": 405857,
          "sell": 494601,
          "net": -88744
        },
        {
          "rank": 5,
          "name": "台新",
          "buy": 488204,
          "sell": 327160,
          "net": 161044
        },
        {
          "rank": 6,
          "name": "群益",
          "buy": 387093,
          "sell": 374096,
          "net": 12997
        },
        {
          "rank": 7,
          "name": "星洲瑞銀",
          "buy": 152854,
          "sell": 521561,
          "net": -368707
        },
        {
          "rank": 8,
          "name": "永豐金",
          "buy": 291260,
          "sell": 202023,
          "net": 89237
        },
        {
          "rank": 9,
          "name": "國泰綜合",
          "buy": 249247,
          "sell": 173800,
          "net": 75447
        },
        {
          "rank": 10,
          "name": "港商野村",
          "buy": 23733,
          "sell": 379815,
          "net": -356082
        },
        {
          "rank": 11,
          "name": "美商高盛亞",
          "buy": 95918,
          "sell": 247750,
          "net": -151832
        },
        {
          "rank": 12,
          "name": "美林證券",
          "buy": 11236,
          "sell": 314886,
          "net": -303650
        },
        {
          "rank": 13,
          "name": "摩根大通",
          "buy": 103087,
          "sell": 209998,
          "net": -106911
        },
        {
          "rank": 14,
          "name": "華南永昌",
          "buy": 197779,
          "sell": 96514,
          "net": 101265
        },
        {
          "rank": 15,
          "name": "統一",
          "buy": 199711,
          "sell": 83416,
          "net": 116295
        }
      ],
      "total_net": -343788
    },
    {
      "rank": 10,
      "name": "上詮",
      "code": "3363",
      "brokers": [
        {
          "rank": 1,
          "name": "元大",
          "buy": 1574433,
          "sell": 1406192,
          "net": 168241
        },
        {
          "rank": 2,
          "name": "凱基",
          "buy": 767420,
          "sell": 789878,
          "net": -22458
        },
        {
          "rank": 3,
          "name": "富邦",
          "buy": 588009,
          "sell": 566759,
          "net": 21250
        },
        {
          "rank": 4,
          "name": "國泰綜合",
          "buy": 385945,
          "sell": 365563,
          "net": 20382
        },
        {
          "rank": 5,
          "name": "群益",
          "buy": 432889,
          "sell": 283306,
          "net": 149583
        },
        {
          "rank": 6,
          "name": "台新",
          "buy": 333500,
          "sell": 360125,
          "net": -26625
        },
        {
          "rank": 7,
          "name": "永豐金",
          "buy": 337805,
          "sell": 344269,
          "net": -6464
        },
        {
          "rank": 8,
          "name": "美商高盛亞",
          "buy": 247313,
          "sell": 270529,
          "net": -23216
        },
        {
          "rank": 9,
          "name": "統一",
          "buy": 156947,
          "sell": 239593,
          "net": -82646
        },
        {
          "rank": 10,
          "name": "摩根大通",
          "buy": 107714,
          "sell": 241632,
          "net": -133918
        },
        {
          "rank": 11,
          "name": "新光",
          "buy": 177908,
          "sell": 161202,
          "net": 16706
        },
        {
          "rank": 12,
          "name": "星洲瑞銀",
          "buy": 196281,
          "sell": 141351,
          "net": 54930
        },
        {
          "rank": 13,
          "name": "華南永昌",
          "buy": 160050,
          "sell": 136835,
          "net": 23215
        },
        {
          "rank": 14,
          "name": "玉山證券",
          "buy": 119198,
          "sell": 117540,
          "net": 1658
        },
        {
          "rank": 15,
          "name": "兆豐",
          "buy": 100979,
          "sell": 112314,
          "net": -11335
        }
      ],
      "total_net": 149303
    },
    {
      "rank": 11,
      "name": "信驊",
      "code": "5274",
      "brokers": [
        {
          "rank": 1,
          "name": "元大",
          "buy": 607590,
          "sell": 672435,
          "net": -64845
        },
        {
          "rank": 2,
          "name": "凱基",
          "buy": 394645,
          "sell": 831065,
          "net": -436420
        },
        {
          "rank": 3,
          "name": "星洲瑞銀",
          "buy": 545990,
          "sell": 654200,
          "net": -108210
        },
        {
          "rank": 4,
          "name": "美林證券",
          "buy": 727915,
          "sell": 438840,
          "net": 289075
        },
        {
          "rank": 5,
          "name": "港商麥格理",
          "buy": 961185,
          "sell": 14885,
          "net": 946300
        },
        {
          "rank": 6,
          "name": "美商高盛亞",
          "buy": 287735,
          "sell": 578515,
          "net": -290780
        },
        {
          "rank": 7,
          "name": "國泰綜合",
          "buy": 151870,
          "sell": 363910,
          "net": -212040
        },
        {
          "rank": 8,
          "name": "永豐金",
          "buy": 257505,
          "sell": 258090,
          "net": -585
        },
        {
          "rank": 9,
          "name": "摩根士丹利",
          "buy": 277010,
          "sell": 212645,
          "net": 64365
        },
        {
          "rank": 10,
          "name": "摩根大通",
          "buy": 106900,
          "sell": 246650,
          "net": -139750
        },
        {
          "rank": 11,
          "name": "群益",
          "buy": 166810,
          "sell": 61240,
          "net": 105570
        },
        {
          "rank": 12,
          "name": "港商野村",
          "buy": 46350,
          "sell": 181600,
          "net": -135250
        },
        {
          "rank": 13,
          "name": "台新",
          "buy": 91820,
          "sell": 122310,
          "net": -30490
        },
        {
          "rank": 14,
          "name": "中國信託證",
          "buy": 106760,
          "sell": 76350,
          "net": 30410
        },
        {
          "rank": 15,
          "name": "花旗環球",
          "buy": 121125,
          "sell": 60215,
          "net": 60910
        }
      ],
      "total_net": 78260
    },
    {
      "rank": 12,
      "name": "萬潤",
      "code": "6187",
      "brokers": [
        {
          "rank": 1,
          "name": "凱基",
          "buy": 881345,
          "sell": 612770,
          "net": 268575
        },
        {
          "rank": 2,
          "name": "國泰綜合",
          "buy": 947525,
          "sell": 312675,
          "net": 634850
        },
        {
          "rank": 3,
          "name": "元大",
          "buy": 527265,
          "sell": 576960,
          "net": -49695
        },
        {
          "rank": 4,
          "name": "富邦",
          "buy": 326385,
          "sell": 404535,
          "net": -78150
        },
        {
          "rank": 5,
          "name": "摩根士丹利",
          "buy": 343895,
          "sell": 332120,
          "net": 11775
        },
        {
          "rank": 6,
          "name": "美林證券",
          "buy": 396900,
          "sell": 117930,
          "net": 278970
        },
        {
          "rank": 7,
          "name": "港商野村",
          "buy": 198710,
          "sell": 241785,
          "net": -43075
        },
        {
          "rank": 8,
          "name": "永豐金",
          "buy": 172340,
          "sell": 267785,
          "net": -95445
        },
        {
          "rank": 9,
          "name": "統一",
          "buy": 132485,
          "sell": 257135,
          "net": -124650
        },
        {
          "rank": 10,
          "name": "台新",
          "buy": 140400,
          "sell": 195735,
          "net": -55335
        },
        {
          "rank": 11,
          "name": "摩根大通",
          "buy": 193390,
          "sell": 139820,
          "net": 53570
        },
        {
          "rank": 12,
          "name": "兆豐",
          "buy": 141410,
          "sell": 190690,
          "net": -49280
        },
        {
          "rank": 13,
          "name": "美商高盛亞",
          "buy": 1320,
          "sell": 237345,
          "net": -236025
        },
        {
          "rank": 14,
          "name": "新光",
          "buy": 100960,
          "sell": 131950,
          "net": -30990
        },
        {
          "rank": 15,
          "name": "群益",
          "buy": 91825,
          "sell": 110755,
          "net": -18930
        }
      ],
      "total_net": 466165
    },
    {
      "rank": 13,
      "name": "精測",
      "code": "6510",
      "brokers": [
        {
          "rank": 1,
          "name": "元大",
          "buy": 1083475,
          "sell": 1119385,
          "net": -35910
        },
        {
          "rank": 2,
          "name": "凱基",
          "buy": 539370,
          "sell": 594945,
          "net": -55575
        },
        {
          "rank": 3,
          "name": "永豐金",
          "buy": 489875,
          "sell": 207095,
          "net": 282780
        },
        {
          "rank": 4,
          "name": "富邦",
          "buy": 287555,
          "sell": 363900,
          "net": -76345
        },
        {
          "rank": 5,
          "name": "摩根士丹利",
          "buy": 335000,
          "sell": 305750,
          "net": 29250
        },
        {
          "rank": 6,
          "name": "美商高盛亞",
          "buy": 165950,
          "sell": 347025,
          "net": -181075
        },
        {
          "rank": 7,
          "name": "星洲瑞銀",
          "buy": 224940,
          "sell": 284365,
          "net": -59425
        },
        {
          "rank": 8,
          "name": "統一",
          "buy": 318490,
          "sell": 155045,
          "net": 163445
        },
        {
          "rank": 9,
          "name": "群益",
          "buy": 170320,
          "sell": 203500,
          "net": -33180
        },
        {
          "rank": 10,
          "name": "華南永昌",
          "buy": 180545,
          "sell": 179690,
          "net": 855
        },
        {
          "rank": 11,
          "name": "台新",
          "buy": 161370,
          "sell": 162380,
          "net": -1010
        },
        {
          "rank": 12,
          "name": "第一金證券",
          "buy": 134880,
          "sell": 153345,
          "net": -18465
        },
        {
          "rank": 13,
          "name": "國泰綜合",
          "buy": 135480,
          "sell": 151070,
          "net": -15590
        },
        {
          "rank": 14,
          "name": "新光",
          "buy": 173695,
          "sell": 91345,
          "net": 82350
        },
        {
          "rank": 15,
          "name": "兆豐",
          "buy": 169645,
          "sell": 79890,
          "net": 89755
        }
      ],
      "total_net": 171860
    },
    {
      "rank": 14,
      "name": "力旺",
      "code": "3529",
      "brokers": [
        {
          "rank": 1,
          "name": "元大",
          "buy": 828675,
          "sell": 811830,
          "net": 16845
        },
        {
          "rank": 2,
          "name": "凱基",
          "buy": 519750,
          "sell": 422395,
          "net": 97355
        },
        {
          "rank": 3,
          "name": "永豐金",
          "buy": 571465,
          "sell": 358620,
          "net": 212845
        },
        {
          "rank": 4,
          "name": "摩根士丹利",
          "buy": 356260,
          "sell": 384335,
          "net": -28075
        },
        {
          "rank": 5,
          "name": "美林證券",
          "buy": 252975,
          "sell": 402920,
          "net": -149945
        },
        {
          "rank": 6,
          "name": "群益",
          "buy": 495000,
          "sell": 99610,
          "net": 395390
        },
        {
          "rank": 7,
          "name": "星洲瑞銀",
          "buy": 115105,
          "sell": 374250,
          "net": -259145
        },
        {
          "rank": 8,
          "name": "美商高盛亞",
          "buy": 148185,
          "sell": 266845,
          "net": -118660
        },
        {
          "rank": 9,
          "name": "富邦",
          "buy": 213410,
          "sell": 199500,
          "net": 13910
        },
        {
          "rank": 10,
          "name": "台新",
          "buy": 178780,
          "sell": 226525,
          "net": -47745
        },
        {
          "rank": 11,
          "name": "國泰綜合",
          "buy": 104690,
          "sell": 237815,
          "net": -133125
        },
        {
          "rank": 12,
          "name": "花旗環球",
          "buy": 267750,
          "sell": 21450,
          "net": 246300
        },
        {
          "rank": 13,
          "name": "統一",
          "buy": 85930,
          "sell": 142475,
          "net": -56545
        },
        {
          "rank": 14,
          "name": "兆豐",
          "buy": 116685,
          "sell": 99705,
          "net": 16980
        },
        {
          "rank": 15,
          "name": "新光",
          "buy": 43570,
          "sell": 166960,
          "net": -123390
        }
      ],
      "total_net": 82995
    },
    {
      "rank": 15,
      "name": "高技",
      "code": "5439",
      "brokers": [
        {
          "rank": 1,
          "name": "元大",
          "buy": 1352057,
          "sell": 1214224,
          "net": 137833
        },
        {
          "rank": 2,
          "name": "凱基",
          "buy": 580378,
          "sell": 672653,
          "net": -92275
        },
        {
          "rank": 3,
          "name": "富邦",
          "buy": 298203,
          "sell": 360374,
          "net": -62171
        },
        {
          "rank": 4,
          "name": "群益",
          "buy": 244204,
          "sell": 242817,
          "net": 1387
        },
        {
          "rank": 5,
          "name": "永豐金",
          "buy": 219492,
          "sell": 229072,
          "net": -9580
        },
        {
          "rank": 6,
          "name": "國泰綜合",
          "buy": 236844,
          "sell": 165751,
          "net": 71093
        },
        {
          "rank": 7,
          "name": "台新",
          "buy": 222936,
          "sell": 173970,
          "net": 48966
        },
        {
          "rank": 8,
          "name": "摩根士丹利",
          "buy": 39045,
          "sell": 293537,
          "net": -254492
        },
        {
          "rank": 9,
          "name": "統一",
          "buy": 188962,
          "sell": 131053,
          "net": 57909
        },
        {
          "rank": 10,
          "name": "港商野村",
          "buy": 64713,
          "sell": 222456,
          "net": -157743
        },
        {
          "rank": 11,
          "name": "星洲瑞銀",
          "buy": 85965,
          "sell": 199446,
          "net": -113481
        },
        {
          "rank": 12,
          "name": "摩根大通",
          "buy": 124401,
          "sell": 137774,
          "net": -13373
        },
        {
          "rank": 13,
          "name": "兆豐",
          "buy": 186264,
          "sell": 57256,
          "net": 129008
        },
        {
          "rank": 14,
          "name": "玉山證券",
          "buy": 126448,
          "sell": 109223,
          "net": 17225
        },
        {
          "rank": 15,
          "name": "新光",
          "buy": 113976,
          "sell": 79629,
          "net": 34347
        }
      ],
      "total_net": -205347
    },
    {
      "rank": 16,
      "name": "雙鴻",
      "code": "3324",
      "brokers": [
        {
          "rank": 1,
          "name": "元大",
          "buy": 841640,
          "sell": 786795,
          "net": 54845
        },
        {
          "rank": 2,
          "name": "凱基",
          "buy": 480805,
          "sell": 733160,
          "net": -252355
        },
        {
          "rank": 3,
          "name": "摩根士丹利",
          "buy": 785830,
          "sell": 108315,
          "net": 677515
        },
        {
          "rank": 4,
          "name": "富邦",
          "buy": 270575,
          "sell": 310065,
          "net": -39490
        },
        {
          "rank": 5,
          "name": "群益",
          "buy": 260445,
          "sell": 308070,
          "net": -47625
        },
        {
          "rank": 6,
          "name": "永豐金",
          "buy": 317385,
          "sell": 156585,
          "net": 160800
        },
        {
          "rank": 7,
          "name": "國泰綜合",
          "buy": 191025,
          "sell": 229760,
          "net": -38735
        },
        {
          "rank": 8,
          "name": "台新",
          "buy": 145390,
          "sell": 216715,
          "net": -71325
        },
        {
          "rank": 9,
          "name": "美商高盛亞",
          "buy": 111655,
          "sell": 229385,
          "net": -117730
        },
        {
          "rank": 10,
          "name": "華南永昌",
          "buy": 138395,
          "sell": 134880,
          "net": 3515
        },
        {
          "rank": 11,
          "name": "星洲瑞銀",
          "buy": 96900,
          "sell": 164245,
          "net": -67345
        },
        {
          "rank": 12,
          "name": "康和",
          "buy": 55630,
          "sell": 173615,
          "net": -117985
        },
        {
          "rank": 13,
          "name": "美林證券",
          "buy": 54460,
          "sell": 127000,
          "net": -72540
        },
        {
          "rank": 14,
          "name": "統一",
          "buy": 85345,
          "sell": 90265,
          "net": -4920
        },
        {
          "rank": 15,
          "name": "國票",
          "buy": 68335,
          "sell": 103485,
          "net": -35150
        }
      ],
      "total_net": 31475
    },
    {
      "rank": 17,
      "name": "家登",
      "code": "3680",
      "brokers": [
        {
          "rank": 1,
          "name": "元大",
          "buy": 812533,
          "sell": 819988,
          "net": -7455
        },
        {
          "rank": 2,
          "name": "凱基",
          "buy": 507737,
          "sell": 520386,
          "net": -12649
        },
        {
          "rank": 3,
          "name": "富邦",
          "buy": 275580,
          "sell": 390422,
          "net": -114842
        },
        {
          "rank": 4,
          "name": "群益",
          "buy": 276650,
          "sell": 266461,
          "net": 10189
        },
        {
          "rank": 5,
          "name": "永豐金",
          "buy": 282693,
          "sell": 238973,
          "net": 43720
        },
        {
          "rank": 6,
          "name": "台新",
          "buy": 264539,
          "sell": 230518,
          "net": 34021
        },
        {
          "rank": 7,
          "name": "摩根士丹利",
          "buy": 199465,
          "sell": 153896,
          "net": 45569
        },
        {
          "rank": 8,
          "name": "國泰綜合",
          "buy": 172717,
          "sell": 167138,
          "net": 5579
        },
        {
          "rank": 9,
          "name": "統一",
          "buy": 177101,
          "sell": 136015,
          "net": 41086
        },
        {
          "rank": 10,
          "name": "摩根大通",
          "buy": 229100,
          "sell": 75665,
          "net": 153435
        },
        {
          "rank": 11,
          "name": "美林證券",
          "buy": 14666,
          "sell": 281562,
          "net": -266896
        },
        {
          "rank": 12,
          "name": "美商高盛亞",
          "buy": 138151,
          "sell": 101589,
          "net": 36562
        },
        {
          "rank": 13,
          "name": "華南永昌",
          "buy": 122554,
          "sell": 88737,
          "net": 33817
        },
        {
          "rank": 14,
          "name": "第一金證券",
          "buy": 108892,
          "sell": 73131,
          "net": 35761
        },
        {
          "rank": 15,
          "name": "新光",
          "buy": 77674,
          "sell": 95858,
          "net": -18184
        }
      ],
      "total_net": 19713
    },
    {
      "rank": 18,
      "name": "良維",
      "code": "6290",
      "brokers": [
        {
          "rank": 1,
          "name": "元大",
          "buy": 922792,
          "sell": 806692,
          "net": 116100
        },
        {
          "rank": 2,
          "name": "凱基",
          "buy": 578975,
          "sell": 938619,
          "net": -359644
        },
        {
          "rank": 3,
          "name": "富邦",
          "buy": 421833,
          "sell": 189778,
          "net": 232055
        },
        {
          "rank": 4,
          "name": "群益",
          "buy": 217717,
          "sell": 244391,
          "net": -26674
        },
        {
          "rank": 5,
          "name": "台新",
          "buy": 243697,
          "sell": 203686,
          "net": 40011
        },
        {
          "rank": 6,
          "name": "摩根士丹利",
          "buy": 221915,
          "sell": 183426,
          "net": 38489
        },
        {
          "rank": 7,
          "name": "永豐金",
          "buy": 164094,
          "sell": 219709,
          "net": -55615
        },
        {
          "rank": 8,
          "name": "國泰綜合",
          "buy": 192054,
          "sell": 157753,
          "net": 34301
        },
        {
          "rank": 9,
          "name": "美商高盛亞",
          "buy": 105225,
          "sell": 173242,
          "net": -68017
        },
        {
          "rank": 10,
          "name": "統一",
          "buy": 147546,
          "sell": 122531,
          "net": 25015
        },
        {
          "rank": 11,
          "name": "華南永昌",
          "buy": 127239,
          "sell": 89861,
          "net": 37378
        },
        {
          "rank": 12,
          "name": "摩根大通",
          "buy": 105091,
          "sell": 104888,
          "net": 203
        },
        {
          "rank": 13,
          "name": "兆豐",
          "buy": 131736,
          "sell": 58752,
          "net": 72984
        },
        {
          "rank": 14,
          "name": "星洲瑞銀",
          "buy": 64182,
          "sell": 109613,
          "net": -45431
        },
        {
          "rank": 15,
          "name": "玉山證券",
          "buy": 79745,
          "sell": 69389,
          "net": 10356
        }
      ],
      "total_net": 51511
    },
    {
      "rank": 19,
      "name": "凱崴",
      "code": "5498",
      "brokers": [
        {
          "rank": 1,
          "name": "富邦",
          "buy": 740545,
          "sell": 964314,
          "net": -223769
        },
        {
          "rank": 2,
          "name": "元大",
          "buy": 731328,
          "sell": 769830,
          "net": -38502
        },
        {
          "rank": 3,
          "name": "凱基",
          "buy": 544085,
          "sell": 505306,
          "net": 38779
        },
        {
          "rank": 4,
          "name": "永豐金",
          "buy": 177706,
          "sell": 263042,
          "net": -85336
        },
        {
          "rank": 5,
          "name": "台新",
          "buy": 167614,
          "sell": 205909,
          "net": -38295
        },
        {
          "rank": 6,
          "name": "國泰綜合",
          "buy": 163558,
          "sell": 187834,
          "net": -24276
        },
        {
          "rank": 7,
          "name": "華南永昌",
          "buy": 124727,
          "sell": 160903,
          "net": -36176
        },
        {
          "rank": 8,
          "name": "群益",
          "buy": 135869,
          "sell": 126830,
          "net": 9039
        },
        {
          "rank": 9,
          "name": "統一",
          "buy": 166976,
          "sell": 86420,
          "net": 80556
        },
        {
          "rank": 10,
          "name": "星洲瑞銀",
          "buy": 174396,
          "sell": 14283,
          "net": 160113
        },
        {
          "rank": 11,
          "name": "兆豐",
          "buy": 82449,
          "sell": 100073,
          "net": -17624
        },
        {
          "rank": 12,
          "name": "玉山證券",
          "buy": 93362,
          "sell": 79013,
          "net": 14349
        },
        {
          "rank": 13,
          "name": "新光",
          "buy": 73229,
          "sell": 73452,
          "net": -223
        },
        {
          "rank": 14,
          "name": "美商高盛亞",
          "buy": 96062,
          "sell": 42610,
          "net": 53452
        },
        {
          "rank": 15,
          "name": "國票",
          "buy": 82780,
          "sell": 54639,
          "net": 28141
        }
      ],
      "total_net": -79772
    },
    {
      "rank": 20,
      "name": "宜鼎",
      "code": "5289",
      "brokers": [
        {
          "rank": 1,
          "name": "凱基",
          "buy": 760920,
          "sell": 654555,
          "net": 106365
        },
        {
          "rank": 2,
          "name": "元大",
          "buy": 693635,
          "sell": 656940,
          "net": 36695
        },
        {
          "rank": 3,
          "name": "富邦",
          "buy": 612180,
          "sell": 368675,
          "net": 243505
        },
        {
          "rank": 4,
          "name": "永豐金",
          "buy": 288530,
          "sell": 196730,
          "net": 91800
        },
        {
          "rank": 5,
          "name": "台新",
          "buy": 139790,
          "sell": 226485,
          "net": -86695
        },
        {
          "rank": 6,
          "name": "美商高盛亞",
          "buy": 115080,
          "sell": 197230,
          "net": -82150
        },
        {
          "rank": 7,
          "name": "群益",
          "buy": 156430,
          "sell": 152210,
          "net": 4220
        },
        {
          "rank": 8,
          "name": "國泰綜合",
          "buy": 104475,
          "sell": 197655,
          "net": -93180
        },
        {
          "rank": 9,
          "name": "華南永昌",
          "buy": 150480,
          "sell": 148250,
          "net": 2230
        },
        {
          "rank": 10,
          "name": "統一",
          "buy": 91940,
          "sell": 116055,
          "net": -24115
        },
        {
          "rank": 11,
          "name": "摩根大通",
          "buy": 95210,
          "sell": 92645,
          "net": 2565
        },
        {
          "rank": 12,
          "name": "國票",
          "buy": 76055,
          "sell": 108390,
          "net": -32335
        },
        {
          "rank": 13,
          "name": "兆豐",
          "buy": 81435,
          "sell": 100340,
          "net": -18905
        },
        {
          "rank": 14,
          "name": "港商野村",
          "buy": 95020,
          "sell": 69690,
          "net": 25330
        },
        {
          "rank": 15,
          "name": "玉山證券",
          "buy": 62050,
          "sell": 85210,
          "net": -23160
        }
      ],
      "total_net": 152170
    },
    {
      "rank": 21,
      "name": "精材",
      "code": "3374",
      "brokers": [
        {
          "rank": 1,
          "name": "元大",
          "buy": 828707,
          "sell": 652978,
          "net": 175729
        },
        {
          "rank": 2,
          "name": "凱基",
          "buy": 424223,
          "sell": 432966,
          "net": -8743
        },
        {
          "rank": 3,
          "name": "富邦",
          "buy": 339228,
          "sell": 212714,
          "net": 126514
        },
        {
          "rank": 4,
          "name": "台新",
          "buy": 215563,
          "sell": 258708,
          "net": -43145
        },
        {
          "rank": 5,
          "name": "國泰綜合",
          "buy": 249413,
          "sell": 139211,
          "net": 110202
        },
        {
          "rank": 6,
          "name": "永豐金",
          "buy": 225539,
          "sell": 156782,
          "net": 68757
        },
        {
          "rank": 7,
          "name": "美商高盛亞",
          "buy": 28757,
          "sell": 254133,
          "net": -225376
        },
        {
          "rank": 8,
          "name": "群益",
          "buy": 149593,
          "sell": 125660,
          "net": 23933
        },
        {
          "rank": 9,
          "name": "星洲瑞銀",
          "buy": 35560,
          "sell": 222559,
          "net": -186999
        },
        {
          "rank": 10,
          "name": "玉山證券",
          "buy": 143039,
          "sell": 77201,
          "net": 65838
        },
        {
          "rank": 11,
          "name": "摩根士丹利",
          "buy": 4156,
          "sell": 198500,
          "net": -194344
        },
        {
          "rank": 12,
          "name": "華南永昌",
          "buy": 124956,
          "sell": 73105,
          "net": 51851
        },
        {
          "rank": 13,
          "name": "兆豐",
          "buy": 122301,
          "sell": 71929,
          "net": 50372
        },
        {
          "rank": 14,
          "name": "統一",
          "buy": 91716,
          "sell": 100447,
          "net": -8731
        },
        {
          "rank": 15,
          "name": "新光",
          "buy": 106202,
          "sell": 67706,
          "net": 38496
        }
      ],
      "total_net": 44354
    },
    {
      "rank": 22,
      "name": "中美晶",
      "code": "5483",
      "brokers": [
        {
          "rank": 1,
          "name": "元大",
          "buy": 660557,
          "sell": 873870,
          "net": -213313
        },
        {
          "rank": 2,
          "name": "凱基",
          "buy": 378560,
          "sell": 360567,
          "net": 17993
        },
        {
          "rank": 3,
          "name": "富邦",
          "buy": 204277,
          "sell": 242473,
          "net": -38196
        },
        {
          "rank": 4,
          "name": "永豐金",
          "buy": 141708,
          "sell": 270776,
          "net": -129068
        },
        {
          "rank": 5,
          "name": "台新",
          "buy": 174793,
          "sell": 192723,
          "net": -17930
        },
        {
          "rank": 6,
          "name": "中國信託證",
          "buy": 267512,
          "sell": 56266,
          "net": 211246
        },
        {
          "rank": 7,
          "name": "群益",
          "buy": 139280,
          "sell": 159554,
          "net": -20274
        },
        {
          "rank": 8,
          "name": "國泰綜合",
          "buy": 144088,
          "sell": 148588,
          "net": -4500
        },
        {
          "rank": 9,
          "name": "統一",
          "buy": 120274,
          "sell": 142922,
          "net": -22648
        },
        {
          "rank": 10,
          "name": "星洲瑞銀",
          "buy": 174300,
          "sell": 53018,
          "net": 121282
        },
        {
          "rank": 11,
          "name": "美商高盛亞",
          "buy": 136166,
          "sell": 79525,
          "net": 56641
        },
        {
          "rank": 12,
          "name": "兆豐",
          "buy": 101316,
          "sell": 62262,
          "net": 39054
        },
        {
          "rank": 13,
          "name": "華南永昌",
          "buy": 67193,
          "sell": 86288,
          "net": -19095
        },
        {
          "rank": 14,
          "name": "國票",
          "buy": 68917,
          "sell": 80879,
          "net": -11962
        },
        {
          "rank": 15,
          "name": "玉山證券",
          "buy": 50499,
          "sell": 95567,
          "net": -45068
        }
      ],
      "total_net": -75838
    },
    {
      "rank": 23,
      "name": "欣銓",
      "code": "3264",
      "brokers": [
        {
          "rank": 1,
          "name": "元大",
          "buy": 1225087,
          "sell": 823489,
          "net": 401598
        },
        {
          "rank": 2,
          "name": "凱基",
          "buy": 483144,
          "sell": 503503,
          "net": -20359
        },
        {
          "rank": 3,
          "name": "富邦",
          "buy": 166543,
          "sell": 290547,
          "net": -124004
        },
        {
          "rank": 4,
          "name": "永豐金",
          "buy": 144293,
          "sell": 138648,
          "net": 5645
        },
        {
          "rank": 5,
          "name": "國泰綜合",
          "buy": 86619,
          "sell": 171435,
          "net": -84816
        },
        {
          "rank": 6,
          "name": "群益",
          "buy": 112127,
          "sell": 128174,
          "net": -16047
        },
        {
          "rank": 7,
          "name": "台新",
          "buy": 71280,
          "sell": 143792,
          "net": -72512
        },
        {
          "rank": 8,
          "name": "美商高盛亞",
          "buy": 90781,
          "sell": 89028,
          "net": 1753
        },
        {
          "rank": 9,
          "name": "中國信託證",
          "buy": 125475,
          "sell": 42015,
          "net": 83460
        },
        {
          "rank": 10,
          "name": "華南永昌",
          "buy": 39648,
          "sell": 124817,
          "net": -85169
        },
        {
          "rank": 11,
          "name": "統一",
          "buy": 63033,
          "sell": 96296,
          "net": -33263
        },
        {
          "rank": 12,
          "name": "港商野村",
          "buy": 153984,
          "sell": 1643,
          "net": 152341
        },
        {
          "rank": 13,
          "name": "新光",
          "buy": 40415,
          "sell": 98148,
          "net": -57733
        },
        {
          "rank": 14,
          "name": "兆豐",
          "buy": 24025,
          "sell": 105421,
          "net": -81396
        },
        {
          "rank": 15,
          "name": "摩根大通",
          "buy": 104160,
          "sell": 8640,
          "net": 95520
        }
      ],
      "total_net": 165018
    },
    {
      "rank": 24,
      "name": "昇達科",
      "code": "3491",
      "brokers": [
        {
          "rank": 1,
          "name": "元大",
          "buy": 702880,
          "sell": 626670,
          "net": 76210
        },
        {
          "rank": 2,
          "name": "凱基",
          "buy": 437215,
          "sell": 464340,
          "net": -27125
        },
        {
          "rank": 3,
          "name": "富邦",
          "buy": 236500,
          "sell": 239300,
          "net": -2800
        },
        {
          "rank": 4,
          "name": "永豐金",
          "buy": 234675,
          "sell": 151005,
          "net": 83670
        },
        {
          "rank": 5,
          "name": "摩根士丹利",
          "buy": 76405,
          "sell": 298040,
          "net": -221635
        },
        {
          "rank": 6,
          "name": "國泰綜合",
          "buy": 164725,
          "sell": 182930,
          "net": -18205
        },
        {
          "rank": 7,
          "name": "台新",
          "buy": 158015,
          "sell": 183945,
          "net": -25930
        },
        {
          "rank": 8,
          "name": "華南永昌",
          "buy": 262560,
          "sell": 56155,
          "net": 206405
        },
        {
          "rank": 9,
          "name": "統一",
          "buy": 135500,
          "sell": 141315,
          "net": -5815
        },
        {
          "rank": 10,
          "name": "群益",
          "buy": 103415,
          "sell": 110475,
          "net": -7060
        },
        {
          "rank": 11,
          "name": "摩根大通",
          "buy": 93060,
          "sell": 117525,
          "net": -24465
        },
        {
          "rank": 12,
          "name": "美商高盛亞",
          "buy": 68635,
          "sell": 127030,
          "net": -58395
        },
        {
          "rank": 13,
          "name": "兆豐",
          "buy": 69600,
          "sell": 87080,
          "net": -17480
        },
        {
          "rank": 14,
          "name": "星洲瑞銀",
          "buy": 110610,
          "sell": 33900,
          "net": 76710
        },
        {
          "rank": 15,
          "name": "玉山證券",
          "buy": 67785,
          "sell": 76290,
          "net": -8505
        }
      ],
      "total_net": 25580
    },
    {
      "rank": 25,
      "name": "新應材",
      "code": "4749",
      "brokers": [
        {
          "rank": 1,
          "name": "元大",
          "buy": 707355,
          "sell": 663475,
          "net": 43880
        },
        {
          "rank": 2,
          "name": "凱基",
          "buy": 332712,
          "sell": 433521,
          "net": -100809
        },
        {
          "rank": 3,
          "name": "台新",
          "buy": 135605,
          "sell": 347878,
          "net": -212273
        },
        {
          "rank": 4,
          "name": "群益",
          "buy": 205772,
          "sell": 210213,
          "net": -4441
        },
        {
          "rank": 5,
          "name": "富邦",
          "buy": 189622,
          "sell": 200011,
          "net": -10389
        },
        {
          "rank": 6,
          "name": "永豐金",
          "buy": 165081,
          "sell": 194202,
          "net": -29121
        },
        {
          "rank": 7,
          "name": "國泰綜合",
          "buy": 180819,
          "sell": 164275,
          "net": 16544
        },
        {
          "rank": 8,
          "name": "星洲瑞銀",
          "buy": 165061,
          "sell": 163486,
          "net": 1575
        },
        {
          "rank": 9,
          "name": "摩根士丹利",
          "buy": 197087,
          "sell": 9919,
          "net": 187168
        },
        {
          "rank": 10,
          "name": "摩根大通",
          "buy": 117551,
          "sell": 78878,
          "net": 38673
        },
        {
          "rank": 11,
          "name": "兆豐",
          "buy": 62850,
          "sell": 128930,
          "net": -66080
        },
        {
          "rank": 12,
          "name": "玉山證券",
          "buy": 96175,
          "sell": 70772,
          "net": 25403
        },
        {
          "rank": 13,
          "name": "統一",
          "buy": 98606,
          "sell": 61004,
          "net": 37602
        },
        {
          "rank": 14,
          "name": "新光",
          "buy": 58865,
          "sell": 62818,
          "net": -3953
        },
        {
          "rank": 15,
          "name": "美商高盛亞",
          "buy": 89300,
          "sell": 25794,
          "net": 63506
        }
      ],
      "total_net": -12715
    },
    {
      "rank": 26,
      "name": "順達",
      "code": "3211",
      "brokers": [
        {
          "rank": 1,
          "name": "元大",
          "buy": 596956,
          "sell": 618477,
          "net": -21521
        },
        {
          "rank": 2,
          "name": "凱基",
          "buy": 450094,
          "sell": 428612,
          "net": 21482
        },
        {
          "rank": 3,
          "name": "富邦",
          "buy": 239018,
          "sell": 272265,
          "net": -33247
        },
        {
          "rank": 4,
          "name": "永豐金",
          "buy": 165158,
          "sell": 198863,
          "net": -33705
        },
        {
          "rank": 5,
          "name": "台新",
          "buy": 174986,
          "sell": 175673,
          "net": -687
        },
        {
          "rank": 6,
          "name": "國泰綜合",
          "buy": 115205,
          "sell": 168248,
          "net": -53043
        },
        {
          "rank": 7,
          "name": "群益",
          "buy": 124614,
          "sell": 153234,
          "net": -28620
        },
        {
          "rank": 8,
          "name": "華南永昌",
          "buy": 125484,
          "sell": 144314,
          "net": -18830
        },
        {
          "rank": 9,
          "name": "星洲瑞銀",
          "buy": 148165,
          "sell": 55767,
          "net": 92398
        },
        {
          "rank": 10,
          "name": "美商高盛亞",
          "buy": 160193,
          "sell": 21980,
          "net": 138213
        },
        {
          "rank": 11,
          "name": "兆豐",
          "buy": 69155,
          "sell": 105005,
          "net": -35850
        },
        {
          "rank": 12,
          "name": "統一",
          "buy": 62053,
          "sell": 89900,
          "net": -27847
        },
        {
          "rank": 13,
          "name": "玉山證券",
          "buy": 52717,
          "sell": 96078,
          "net": -43361
        },
        {
          "rank": 14,
          "name": "新光",
          "buy": 62239,
          "sell": 68691,
          "net": -6452
        },
        {
          "rank": 15,
          "name": "摩根士丹利",
          "buy": 76190,
          "sell": 38304,
          "net": 37886
        }
      ],
      "total_net": -13184
    },
    {
      "rank": 27,
      "name": "合晶",
      "code": "6182",
      "brokers": [
        {
          "rank": 1,
          "name": "元大",
          "buy": 814969,
          "sell": 758882,
          "net": 56087
        },
        {
          "rank": 2,
          "name": "凱基",
          "buy": 474021,
          "sell": 296966,
          "net": 177055
        },
        {
          "rank": 3,
          "name": "富邦",
          "buy": 265893,
          "sell": 266373,
          "net": -480
        },
        {
          "rank": 4,
          "name": "群益",
          "buy": 114576,
          "sell": 209253,
          "net": -94677
        },
        {
          "rank": 5,
          "name": "國泰綜合",
          "buy": 148226,
          "sell": 135571,
          "net": 12655
        },
        {
          "rank": 6,
          "name": "台新",
          "buy": 113388,
          "sell": 160252,
          "net": -46864
        },
        {
          "rank": 7,
          "name": "永豐金",
          "buy": 114505,
          "sell": 159127,
          "net": -44622
        },
        {
          "rank": 8,
          "name": "兆豐",
          "buy": 147460,
          "sell": 91350,
          "net": 56110
        },
        {
          "rank": 9,
          "name": "統一",
          "buy": 108377,
          "sell": 108776,
          "net": -399
        },
        {
          "rank": 10,
          "name": "華南永昌",
          "buy": 65715,
          "sell": 94074,
          "net": -28359
        },
        {
          "rank": 11,
          "name": "國票",
          "buy": 111090,
          "sell": 36431,
          "net": 74659
        },
        {
          "rank": 12,
          "name": "摩根士丹利",
          "buy": 104141,
          "sell": 28795,
          "net": 75346
        },
        {
          "rank": 13,
          "name": "美商高盛亞",
          "buy": 77828,
          "sell": 46206,
          "net": 31622
        },
        {
          "rank": 14,
          "name": "玉山證券",
          "buy": 50685,
          "sell": 67887,
          "net": -17202
        },
        {
          "rank": 15,
          "name": "新光",
          "buy": 56837,
          "sell": 61364,
          "net": -4527
        }
      ],
      "total_net": 246404
    },
    {
      "rank": 28,
      "name": "弘塑",
      "code": "3131",
      "brokers": [
        {
          "rank": 1,
          "name": "元大",
          "buy": 480075,
          "sell": 560295,
          "net": -80220
        },
        {
          "rank": 2,
          "name": "凱基",
          "buy": 558630,
          "sell": 364330,
          "net": 194300
        },
        {
          "rank": 3,
          "name": "星洲瑞銀",
          "buy": 312285,
          "sell": 212725,
          "net": 99560
        },
        {
          "rank": 4,
          "name": "美林證券",
          "buy": 32905,
          "sell": 466685,
          "net": -433780
        },
        {
          "rank": 5,
          "name": "摩根士丹利",
          "buy": 225295,
          "sell": 216815,
          "net": 8480
        },
        {
          "rank": 6,
          "name": "台新",
          "buy": 231755,
          "sell": 209200,
          "net": 22555
        },
        {
          "rank": 7,
          "name": "富邦",
          "buy": 180095,
          "sell": 109185,
          "net": 70910
        },
        {
          "rank": 8,
          "name": "永豐金",
          "buy": 104960,
          "sell": 135440,
          "net": -30480
        },
        {
          "rank": 9,
          "name": "國泰綜合",
          "buy": 140935,
          "sell": 79080,
          "net": 61855
        },
        {
          "rank": 10,
          "name": "摩根大通",
          "buy": 128940,
          "sell": 65680,
          "net": 63260
        },
        {
          "rank": 11,
          "name": "兆豐",
          "buy": 121575,
          "sell": 52990,
          "net": 68585
        },
        {
          "rank": 12,
          "name": "群益",
          "buy": 127710,
          "sell": 42925,
          "net": 84785
        },
        {
          "rank": 13,
          "name": "統一",
          "buy": 82400,
          "sell": 76050,
          "net": 6350
        },
        {
          "rank": 14,
          "name": "新光",
          "buy": 67070,
          "sell": 72335,
          "net": -5265
        },
        {
          "rank": 15,
          "name": "華南永昌",
          "buy": 25970,
          "sell": 66235,
          "net": -40265
        }
      ],
      "total_net": 90630
    },
    {
      "rank": 29,
      "name": "華星光",
      "code": "4979",
      "brokers": [
        {
          "rank": 1,
          "name": "元大",
          "buy": 315670,
          "sell": 728919,
          "net": -413249
        },
        {
          "rank": 2,
          "name": "統一",
          "buy": 225705,
          "sell": 453819,
          "net": -228114
        },
        {
          "rank": 3,
          "name": "國泰綜合",
          "buy": 517843,
          "sell": 57687,
          "net": 460156
        },
        {
          "rank": 4,
          "name": "星洲瑞銀",
          "buy": 514432,
          "sell": 26902,
          "net": 487530
        },
        {
          "rank": 5,
          "name": "富邦",
          "buy": 179948,
          "sell": 333353,
          "net": -153405
        },
        {
          "rank": 6,
          "name": "凱基",
          "buy": 227794,
          "sell": 250943,
          "net": -23149
        },
        {
          "rank": 7,
          "name": "摩根士丹利",
          "buy": 267410,
          "sell": 134813,
          "net": 132597
        },
        {
          "rank": 8,
          "name": "台新",
          "buy": 92846,
          "sell": 164134,
          "net": -71288
        },
        {
          "rank": 9,
          "name": "群益",
          "buy": 74516,
          "sell": 137269,
          "net": -62753
        },
        {
          "rank": 10,
          "name": "中國信託證",
          "buy": 51201,
          "sell": 158476,
          "net": -107275
        },
        {
          "rank": 11,
          "name": "永豐金",
          "buy": 87925,
          "sell": 100866,
          "net": -12941
        },
        {
          "rank": 12,
          "name": "華南永昌",
          "buy": 43545,
          "sell": 104188,
          "net": -60643
        },
        {
          "rank": 13,
          "name": "兆豐",
          "buy": 56967,
          "sell": 59828,
          "net": -2861
        },
        {
          "rank": 14,
          "name": "美商高盛亞",
          "buy": 35772,
          "sell": 66219,
          "net": -30447
        },
        {
          "rank": 15,
          "name": "玉山證券",
          "buy": 39706,
          "sell": 41258,
          "net": -1552
        }
      ],
      "total_net": -87394
    },
    {
      "rank": 30,
      "name": "IET-KY",
      "code": "4971",
      "brokers": [
        {
          "rank": 1,
          "name": "元大",
          "buy": 490988,
          "sell": 461883,
          "net": 29105
        },
        {
          "rank": 2,
          "name": "星洲瑞銀",
          "buy": 269085,
          "sell": 319061,
          "net": -49976
        },
        {
          "rank": 3,
          "name": "凱基",
          "buy": 301131,
          "sell": 208819,
          "net": 92312
        },
        {
          "rank": 4,
          "name": "永豐金",
          "buy": 295275,
          "sell": 186991,
          "net": 108284
        },
        {
          "rank": 5,
          "name": "富邦",
          "buy": 237429,
          "sell": 235524,
          "net": 1905
        },
        {
          "rank": 6,
          "name": "統一",
          "buy": 117128,
          "sell": 210147,
          "net": -93019
        },
        {
          "rank": 7,
          "name": "華南永昌",
          "buy": 126723,
          "sell": 141552,
          "net": -14829
        },
        {
          "rank": 8,
          "name": "台新",
          "buy": 122653,
          "sell": 134833,
          "net": -12180
        },
        {
          "rank": 9,
          "name": "國泰綜合",
          "buy": 136457,
          "sell": 107484,
          "net": 28973
        },
        {
          "rank": 10,
          "name": "美商高盛亞",
          "buy": 25725,
          "sell": 180927,
          "net": -155202
        },
        {
          "rank": 11,
          "name": "摩根大通",
          "buy": 63236,
          "sell": 136313,
          "net": -73077
        },
        {
          "rank": 12,
          "name": "群益",
          "buy": 90043,
          "sell": 106667,
          "net": -16624
        },
        {
          "rank": 13,
          "name": "新光",
          "buy": 91269,
          "sell": 65016,
          "net": 26253
        },
        {
          "rank": 14,
          "name": "中國信託證",
          "buy": 73610,
          "sell": 77496,
          "net": -3886
        },
        {
          "rank": 15,
          "name": "玉山證券",
          "buy": 105576,
          "sell": 40181,
          "net": 65395
        }
      ],
      "total_net": -66566
    }
  ]
}